{"location": {"name": "", "lat": 52.09, "long": 5.12, "tz": "Europe/Amsterdam"}, "sun events": {"Day ends": "2025-11-10 16:55 CET", "Civil twilight ends": "2025-11-10 17:31 CET", "Nautical twilight ends": "2025-11-10 18:12 CET", "Astronomical twilight ends": "2025-11-10 18:52 CET", "Astronomical twilight starts": "2025-11-11 05:55 CET", "Nautical twilight starts": "2025-11-11 06:34 CET", "Civil twilight starts": "2025-11-11 07:15 CET", "Day starts": "2025-11-11 07:52 CET"}, "moon events": {"Set": "2025-11-10 13:39 CET", "Rise": "2025-11-10 21:26 CET", "Moon phase": 63.1}, "session events": {"start_at": -12.0, "start_time": "2025-11-10 18:14 CET", "end_time": "2025-11-11 06:33 CET"}, "limits": {"mag": 19.0, "alt": 0.0, "sun_elong": 0.0, "moon_elong": 0.0}, "comet_list": [{"comet_type": "C", "comet_name": "C/2023 H5", "comet_fullname": "C/2023 H5 (Lemmon)", "mpc_name": "CK23H050", "best_time": "2025-11-10 18:14", "orbit_calc_source": 1, "magnitude": 16.7, "best_ra": "15:41:44.92", "best_dec": "63:21:58.6", "best_alt": 49.5, "sun_elongation": 81.0, "moon_elongation": 79.0, "constelation": "Draco", "rise_time": "2025-11-10 18:14", "set_time": "2025-11-11 06:33", "motion": 0.89, "pa": 90.0, "trend": "steady"}, {"comet_type": "C", "comet_name": "C/2024 G6", "comet_fullname": "C/2024 G6 (ATLAS)", "mpc_name": "CK24G060", "best_time": "2025-11-10 18:14", "orbit_calc_source": 3, "magnitude": 18.0, "best_ra": "16:07:13.56", "best_dec": "-9:40:13.3", "best_alt": 3.3, "sun_elongation": 17.0, "moon_elongation": 120.0, "constelation": "Scorpius", "rise_time": "2025-11-10 18:14", "set_time": "2025-11-10 18:39", "motion": 0.27, "pa": 69.0, "trend": "steady"}, {"comet_type": "C", "comet_name": "C/2021 G2", "comet_fullname": "C/2021 G2 (Atlas)", "mpc_name": "CK21G020", "best_time": "2025-11-10 18:14", "orbit_calc_source": 1, "magnitude": 15.0, "best_ra": "16:10:14.25", "best_dec": "-1:18:35.9", "best_alt": 10.4, "sun_elongation": 23.0, "moon_elongation": 118.0, "constelation": "Serpens Caput", "rise_time": "2025-11-10 18:14", "set_time": "2025-11-10 19:26", "motion": 0.51, "pa": 88.0, "trend": "steady"}, {"comet_type": "C", "comet_name": "C/2025 T1", "comet_fullname": "C/2025 T1 (ATLAS)", "mpc_name": "CK25T010", "best_time": "2025-11-10 18:14", "orbit_calc_source": 0, "magnitude": 10.8, "best_ra": "16:24:52.19", "best_dec": "50:32:56.6", "best_alt": 49.3, "sun_elongation": 70.0, "moon_elongation": 91.0, "constelation": "Hercules", "rise_time": "2025-11-10 18:14", "set_time": "2025-11-11 06:33", "motion": 5.47, "pa": 115.0, "trend": "bright"}, {"comet_type": "C", "comet_name": "C/2025 A6", "comet_fullname": "C/2025 A6 (Lemmon)", "mpc_name": "CK25A060", "best_time": "2025-11-10 18:14", "orbit_calc_source": 0, "magnitude": 4.9, "best_ra": "17:02:19.11", "best_dec": "-12:16:46.2", "best_alt": 8.6, "sun_elongation": 29.0, "moon_elongation": 134.0, "constelation": "Ophiuchus", "rise_time": "2025-11-10 18:14", "set_time": "2025-11-10 19:19", "motion": 3.1, "pa": 157.0, "trend": "fade"}, {"comet_type": "C", "comet_name": "C/2024 E1", "comet_fullname": "C/2024 E1 (Wierzchos)", "mpc_name": "CK24E010", "best_time": "2025-11-10 18:14", "orbit_calc_source": 0, "magnitude": 12.0, "best_ra": "17:03:44.06", "best_dec": "3:21:36.7", "best_alt": 21.9, "sun_elongation": 36.0, "moon_elongation": 127.0, "constelation": "Ophiuchus", "rise_time": "2025-11-10 18:14", "set_time": "2025-11-10 20:43", "motion": 1.61, "pa": 141.0, "trend": "bright"}, {"comet_type": "C", "comet_name": "C/2024 N3", "comet_fullname": "C/2024 N3 (Sarneczky)", "mpc_name": "CK24N030", "best_time": "2025-11-10 18:14", "orbit_calc_source": 3, "magnitude": 19.0, "best_ra": "17:08:46.94", "best_dec": "36:35:48.6", "best_alt": 47.9, "sun_elongation": 61.0, "moon_elongation": 107.0, "constelation": "Hercules", "rise_time": "2025-11-10 18:14", "set_time": "2025-11-11 01:31", "motion": 0.6, "pa": 139.0, "trend": "steady"}, {"comet_type": "P", "comet_name": "141P-B", "comet_fullname": "141P-B/Machholz", "mpc_name": "141P-B", "best_time": "2025-11-10 18:14", "orbit_calc_source": 3, "magnitude": 14.8, "best_ra": "17:28:03.31", "best_dec": "-14:25:18.6", "best_alt": 9.9, "sun_elongation": 35.0, "moon_elongation": 140.0, "constelation": "Serpens Cauda", "rise_time": "2025-11-10 18:14", "set_time": "2025-11-10 19:33", "motion": 1.04, "pa": 101.0, "trend": "bright"}, {"comet_type": "C", "comet_name": "C/2024 G4", "comet_fullname": "C/2024 G4 (PANSTARRS)", "mpc_name": "CK24G040", "best_time": "2025-11-10 18:14", "orbit_calc_source": 3, "magnitude": 18.8, "best_ra": "17:40:23.39", "best_dec": "2:29:24.5", "best_alt": 26.1, "sun_elongation": 43.0, "moon_elongation": 135.0, "constelation": "Ophiuchus", "rise_time": "2025-11-10 18:14", "set_time": "2025-11-10 21:15", "motion": 0.64, "pa": 108.0, "trend": "steady"}, {"comet_type": "C", "comet_name": "C/2023 A3", "comet_fullname": "C/2023 A3 (Tsuchinshan-ATLAS)", "mpc_name": "CK23A030", "best_time": "2025-11-10 18:14", "orbit_calc_source": 1, "magnitude": 17.8, "best_ra": "18:07:17.33", "best_dec": "13:00:36.8", "best_alt": 38.5, "sun_elongation": 54.0, "moon_elongation": 133.0, "constelation": "Ophiuchus", "rise_time": "2025-11-10 18:14", "set_time": "2025-11-10 22:38", "motion": 0.3, "pa": 121.0, "trend": "fade"}, {"comet_type": "C", "comet_name": "C/2025 R1", "comet_fullname": "C/2025 R1 (ATLAS)", "mpc_name": "CK25R010", "best_time": "2025-11-10 18:14", "orbit_calc_source": 3, "magnitude": 18.3, "best_ra": "18:42:15.83", "best_dec": "50:13:58.9", "best_alt": 69.2, "sun_elongation": 83.0, "moon_elongation": 104.0, "constelation": "Draco", "rise_time": "2025-11-10 18:14", "set_time": "2025-11-11 06:33", "motion": 1.94, "pa": 177.0, "trend": "fade"}, {"comet_type": "C", "comet_name": "C/2024 J3", "comet_fullname": "C/2024 J3 (ATLAS)", "mpc_name": "CK24J030", "best_time": "2025-11-10 18:14", "orbit_calc_source": 1, "magnitude": 15.7, "best_ra": "18:43:41.52", "best_dec": "-8:44:15.8", "best_alt": 23.0, "sun_elongation": 54.0, "moon_elongation": 155.0, "constelation": "Scutum", "rise_time": "2025-11-10 18:14", "set_time": "2025-11-10 21:20", "motion": 0.34, "pa": 60.0, "trend": "steady"}, {"comet_type": "C", "comet_name": "C/2023 R1", "comet_fullname": "C/2023 R1 (PANSTARRS)", "mpc_name": "CK23R010", "best_time": "2025-11-10 18:14", "orbit_calc_source": 1, "magnitude": 15.9, "best_ra": "19:14:17.49", "best_dec": "3:25:30.3", "best_alt": 37.0, "sun_elongation": 65.0, "moon_elongation": 150.0, "constelation": "Aquila", "rise_time": "2025-11-10 18:14", "set_time": "2025-11-10 22:53", "motion": 0.39, "pa": 190.0, "trend": "steady"}, {"comet_type": "P", "comet_name": "65P", "comet_fullname": "65P/Gunn", "mpc_name": "0065P", "best_time": "2025-11-10 18:14", "orbit_calc_source": 1, "magnitude": 17.2, "best_ra": "19:33:35.16", "best_dec": "-29:17:58.0", "best_alt": 6.8, "sun_elongation": 62.0, "moon_elongation": 169.0, "constelation": "Sagittarius", "rise_time": "2025-11-10 18:14", "set_time": "2025-11-10 19:54", "motion": 0.81, "pa": 78.0, "trend": "fade"}, {"comet_type": "P", "comet_name": "491P", "comet_fullname": "491P/Spacewatch-PANSTARRS", "mpc_name": "0491P", "best_time": "2025-11-10 18:14", "orbit_calc_source": 3, "magnitude": 18.9, "best_ra": "20:05:58.57", "best_dec": "-20:14:40.7", "best_alt": 16.9, "sun_elongation": 71.0, "moon_elongation": 177.0, "constelation": "Sagittarius", "rise_time": "2025-11-10 18:14", "set_time": "2025-11-10 21:35", "motion": 0.49, "pa": 72.0, "trend": "fade"}, {"comet_type": "P", "comet_name": "502P", "comet_fullname": "502P/NEAT", "mpc_name": "0502P", "best_time": "2025-11-10 18:14", "orbit_calc_source": 3, "magnitude": 18.0, "best_ra": "20:10:34.98", "best_dec": "-11:20:25.5", "best_alt": 25.9, "sun_elongation": 74.0, "moon_elongation": 168.0, "constelation": "Capricornus", "rise_time": "2025-11-10 18:14", "set_time": "2025-11-10 22:33", "motion": 0.48, "pa": 81.0, "trend": "fade"}, {"comet_type": "N", "comet_name": "P/1996 R2", "comet_fullname": "P/1996 R2 (Lagerkvist)", "mpc_name": "PJ96R020", "best_time": "2025-11-10 18:14", "orbit_calc_source": 3, "magnitude": 18.5, "best_ra": "20:11:24.43", "best_dec": "-22:30:36.6", "best_alt": 14.8, "sun_elongation": 72.0, "moon_elongation": 180.0, "constelation": "Capricornus", "rise_time": "2025-11-10 18:14", "set_time": "2025-11-10 21:26", "motion": 0.72, "pa": 75.0, "trend": "steady"}, {"comet_type": "P", "comet_name": "78P", "comet_fullname": "78P/Gehrels", "mpc_name": "0078P", "best_time": "2025-11-10 18:14", "orbit_calc_source": 1, "magnitude": 16.9, "best_ra": "20:24:12.63", "best_dec": "-13:36:41.2", "best_alt": 24.0, "sun_elongation": 77.0, "moon_elongation": 170.0, "constelation": "Capricornus", "rise_time": "2025-11-10 18:14", "set_time": "2025-11-10 22:34", "motion": 0.68, "pa": 84.0, "trend": "bright"}, {"comet_type": "P", "comet_name": "261P", "comet_fullname": "261P/Larson", "mpc_name": "0261P", "best_time": "2025-11-10 18:14", "orbit_calc_source": 3, "magnitude": 18.5, "best_ra": "20:47:57.05", "best_dec": "-12:52:01.4", "best_alt": 25.1, "sun_elongation": 82.0, "moon_elongation": 167.0, "constelation": "Aquarius", "rise_time": "2025-11-10 18:14", "set_time": "2025-11-10 23:02", "motion": 1.05, "pa": 74.0, "trend": "fade"}, {"comet_type": "P", "comet_name": "93P", "comet_fullname": "93P/Lovas", "mpc_name": "0093P", "best_time": "2025-11-10 18:24", "orbit_calc_source": 3, "magnitude": 16.9, "best_ra": "21:05:33.38", "best_dec": "-17:03:40.8", "best_alt": 20.9, "sun_elongation": 85.0, "moon_elongation": 166.0, "constelation": "Capricornus", "rise_time": "2025-11-10 18:14", "set_time": "2025-11-10 22:55", "motion": 0.63, "pa": 58.0, "trend": "bright"}, {"comet_type": "P", "comet_name": "362P", "comet_fullname": "362P/Spacewatch", "mpc_name": "0362P", "best_time": "2025-11-10 18:47", "orbit_calc_source": 3, "magnitude": 18.4, "best_ra": "21:28:47.71", "best_dec": "-4:56:43.0", "best_alt": 33.0, "sun_elongation": 94.0, "moon_elongation": 155.0, "constelation": "Aquarius", "rise_time": "2025-11-10 18:14", "set_time": "2025-11-11 00:25", "motion": 0.37, "pa": 100.0, "trend": "fade"}, {"comet_type": "P", "comet_name": "243P", "comet_fullname": "243P/NEAT", "mpc_name": "0243P", "best_time": "2025-11-10 18:48", "orbit_calc_source": 3, "magnitude": 18.4, "best_ra": "21:29:09.77", "best_dec": "-23:07:03.5", "best_alt": 14.9, "sun_elongation": 89.0, "moon_elongation": 163.0, "constelation": "Capricornus", "rise_time": "2025-11-10 18:14", "set_time": "2025-11-10 22:39", "motion": 0.68, "pa": 65.0, "trend": "fade"}, {"comet_type": "C", "comet_name": "C/2024 R4", "comet_fullname": "C/2024 R4 (PANSTARRS)", "mpc_name": "CK24R040", "best_time": "2025-11-10 18:50", "orbit_calc_source": 1, "magnitude": 16.9, "best_ra": "21:31:07.19", "best_dec": "21:51:14.8", "best_alt": 59.8, "sun_elongation": 102.0, "moon_elongation": 132.0, "constelation": "Pegasus", "rise_time": "2025-11-10 18:14", "set_time": "2025-11-11 02:57", "motion": 0.15, "pa": 228.0, "trend": "steady"}, {"comet_type": "P", "comet_name": "188P", "comet_fullname": "188P/LINEAR-Mueller", "mpc_name": "0188P", "best_time": "2025-11-10 19:05", "orbit_calc_source": 3, "magnitude": 17.9, "best_ra": "21:46:45.41", "best_dec": "-16:36:35.1", "best_alt": 21.3, "sun_elongation": 95.0, "moon_elongation": 157.0, "constelation": "Capricornus", "rise_time": "2025-11-10 18:14", "set_time": "2025-11-10 23:39", "motion": 0.53, "pa": 52.0, "trend": "steady"}, {"comet_type": "N", "comet_name": "P/1999 RO28", "comet_fullname": "P/1999 RO28 (LONEOS)", "mpc_name": "PJ99R28O", "best_time": "2025-11-10 19:09", "orbit_calc_source": 3, "magnitude": 18.9, "best_ra": "21:50:09.87", "best_dec": "-28:38:54.1", "best_alt": 9.4, "sun_elongation": 91.0, "moon_elongation": 158.0, "constelation": "Piscis Austrinus", "rise_time": "2025-11-10 18:14", "set_time": "2025-11-10 22:17", "motion": 2.99, "pa": 77.0, "trend": "steady"}, {"comet_type": "C", "comet_name": "C/2023 C2", "comet_fullname": "C/2023 C2 (ATLAS)", "mpc_name": "CK23C020", "best_time": "2025-11-10 19:37", "orbit_calc_source": 1, "magnitude": 16.7, "best_ra": "22:18:36.27", "best_dec": "53:25:54.0", "best_alt": 88.7, "sun_elongation": 115.0, "moon_elongation": 99.0, "constelation": "Lacerta", "rise_time": "2025-11-10 18:14", "set_time": "2025-11-11 06:33", "motion": 0.33, "pa": 167.0, "trend": "fade"}, {"comet_type": "P", "comet_name": "145P", "comet_fullname": "145P/Shoemaker-Levy", "mpc_name": "0145P", "best_time": "2025-11-10 19:47", "orbit_calc_source": 3, "magnitude": 17.5, "best_ra": "22:29:01.83", "best_dec": "-16:33:49.8", "best_alt": 21.4, "sun_elongation": 104.0, "moon_elongation": 148.0, "constelation": "Aquarius", "rise_time": "2025-11-10 18:14", "set_time": "2025-11-11 00:21", "motion": 0.72, "pa": 40.0, "trend": "steady"}, {"comet_type": "C", "comet_name": "C/2011 J2", "comet_fullname": "C/2011 J2 (LINEAR)", "mpc_name": "CK11J020", "best_time": "2025-11-10 19:49", "orbit_calc_source": 3, "magnitude": 18.6, "best_ra": "22:30:55.89", "best_dec": "-18:33:32.7", "best_alt": 19.4, "sun_elongation": 104.0, "moon_elongation": 148.0, "constelation": "Aquarius", "rise_time": "2025-11-10 18:14", "set_time": "2025-11-11 00:11", "motion": 0.11, "pa": 234.0, "trend": "fade"}, {"comet_type": "C", "comet_name": "C/2022 E2", "comet_fullname": "C/2022 E2 (ATLAS)", "mpc_name": "CK22E020", "best_time": "2025-11-10 19:54", "orbit_calc_source": 1, "magnitude": 16.0, "best_ra": "22:36:11.91", "best_dec": "42:36:13.9", "best_alt": 80.5, "sun_elongation": 118.0, "moon_elongation": 107.0, "constelation": "Lacerta", "rise_time": "2025-11-10 18:14", "set_time": "2025-11-11 06:33", "motion": 0.72, "pa": 203.0, "trend": "fade"}, {"comet_type": "P", "comet_name": "47P", "comet_fullname": "47P/Ashbrook-Jackson", "mpc_name": "0047P", "best_time": "2025-11-10 20:01", "orbit_calc_source": 1, "magnitude": 16.4, "best_ra": "22:42:29.46", "best_dec": "-7:49:14.6", "best_alt": 30.1, "sun_elongation": 111.0, "moon_elongation": 142.0, "constelation": "Aquarius", "rise_time": "2025-11-10 18:14", "set_time": "2025-11-11 01:23", "motion": 0.34, "pa": 39.0, "trend": "fade"}, {"comet_type": "P", "comet_name": "131P", "comet_fullname": "131P/Mueller", "mpc_name": "0131P", "best_time": "2025-11-10 20:11", "orbit_calc_source": 3, "magnitude": 16.4, "best_ra": "22:52:59.29", "best_dec": "-1:57:44.0", "best_alt": 36.0, "sun_elongation": 115.0, "moon_elongation": 137.0, "constelation": "Pisces", "rise_time": "2025-11-10 18:14", "set_time": "2025-11-11 02:04", "motion": 0.32, "pa": 99.0, "trend": "fade"}, {"comet_type": "P", "comet_name": "295P", "comet_fullname": "295P/LINEAR", "mpc_name": "0295P", "best_time": "2025-11-10 20:17", "orbit_calc_source": 3, "magnitude": 18.8, "best_ra": "22:58:20.25", "best_dec": "-10:52:25.0", "best_alt": 27.1, "sun_elongation": 113.0, "moon_elongation": 140.0, "constelation": "Aquarius", "rise_time": "2025-11-10 18:14", "set_time": "2025-11-11 01:23", "motion": 0.27, "pa": 347.0, "trend": "steady"}, {"comet_type": "C", "comet_name": "C/2025 R2", "comet_fullname": "C/2025 R2 (SWAN)", "mpc_name": "CK25R020", "best_time": "2025-11-10 20:22", "orbit_calc_source": 0, "magnitude": 9.3, "best_ra": "23:03:21.39", "best_dec": "3:36:15.1", "best_alt": 41.5, "sun_elongation": 119.0, "moon_elongation": 132.0, "constelation": "Pisces", "rise_time": "2025-11-10 18:14", "set_time": "2025-11-11 02:45", "motion": 3.18, "pa": 73.0, "trend": "fade"}, {"comet_type": "C", "comet_name": "C/2025 R3", "comet_fullname": "C/2025 R3 (PANSTARRS)", "mpc_name": "CK25R030", "best_time": "2025-11-10 20:28", "orbit_calc_source": 3, "magnitude": 18.4, "best_ra": "23:09:55.35", "best_dec": "33:10:08.4", "best_alt": 71.1, "sun_elongation": 125.0, "moon_elongation": 111.0, "constelation": "Pegasus", "rise_time": "2025-11-10 18:14", "set_time": "2025-11-11 06:20", "motion": 1.32, "pa": 238.0, "trend": "bright"}, {"comet_type": "N", "comet_name": "P/2016 G1", "comet_fullname": "P/2016 G1 (PANSTARRS)", "mpc_name": "PK16G010", "best_time": "2025-11-10 21:06", "orbit_calc_source": 3, "magnitude": 18.4, "best_ra": "23:48:14.56", "best_dec": "0:51:26.3", "best_alt": 38.8, "sun_elongation": 129.0, "moon_elongation": 124.0, "constelation": "Pisces", "rise_time": "2025-11-10 18:14", "set_time": "2025-11-11 03:13", "motion": 0.26, "pa": 137.0, "trend": "fade"}, {"comet_type": "P", "comet_name": "128P", "comet_fullname": "128P/Shoemaker-Holt", "mpc_name": "0128P", "best_time": "2025-11-10 21:26", "orbit_calc_source": 3, "magnitude": 15.8, "best_ra": "0:08:13.30", "best_dec": "2:56:42.3", "best_alt": 40.9, "sun_elongation": 134.0, "moon_elongation": 119.0, "constelation": "Pisces", "rise_time": "2025-11-10 18:14", "set_time": "2025-11-11 03:44", "motion": 0.15, "pa": 224.0, "trend": "steady"}, {"comet_type": "P", "comet_name": "302P", "comet_fullname": "302P/Lemmon-PANSTARRS", "mpc_name": "0302P", "best_time": "2025-11-10 21:38", "orbit_calc_source": 1, "magnitude": 16.7, "best_ra": "0:19:34.52", "best_dec": "-5:53:03.9", "best_alt": 32.1, "sun_elongation": 133.0, "moon_elongation": 120.0, "constelation": "Pisces", "rise_time": "2025-11-10 18:14", "set_time": "2025-11-11 03:10", "motion": 0.12, "pa": 278.0, "trend": "fade"}, {"comet_type": "P", "comet_name": "128P-B", "comet_fullname": "128P-B/Shoemaker-Holt", "mpc_name": "128P-B", "best_time": "2025-11-10 22:04", "orbit_calc_source": 3, "magnitude": 15.5, "best_ra": "0:45:59.29", "best_dec": "6:14:22.3", "best_alt": 44.2, "sun_elongation": 144.0, "moon_elongation": 110.0, "constelation": "Pisces", "rise_time": "2025-11-10 18:14", "set_time": "2025-11-11 04:39", "motion": 0.25, "pa": 234.0, "trend": "steady"}, {"comet_type": "N", "comet_name": "P/2023 M4", "comet_fullname": "P/2023 M4 (ATLAS)", "mpc_name": "PK23M040", "best_time": "2025-11-10 22:27", "orbit_calc_source": 3, "magnitude": 18.9, "best_ra": "1:09:36.89", "best_dec": "17:01:23.0", "best_alt": 54.9, "sun_elongation": 152.0, "moon_elongation": 100.0, "constelation": "Pisces", "rise_time": "2025-11-10 18:14", "set_time": "2025-11-11 06:03", "motion": 0.26, "pa": 240.0, "trend": "steady"}, {"comet_type": "A", "comet_name": "A/2025 S2", "comet_fullname": "A/2025 S2", "mpc_name": "AK25S020", "best_time": "2025-11-10 22:29", "orbit_calc_source": 3, "magnitude": 17.1, "best_ra": "1:11:11.92", "best_dec": "7:38:04.1", "best_alt": 45.6, "sun_elongation": 151.0, "moon_elongation": 104.0, "constelation": "Pisces", "rise_time": "2025-11-10 18:14", "set_time": "2025-11-11 05:10", "motion": 4.05, "pa": 291.0, "trend": "steady"}, {"comet_type": "P", "comet_name": "331P", "comet_fullname": "331P/Gibbs", "mpc_name": "0331P", "best_time": "2025-11-10 22:54", "orbit_calc_source": 3, "magnitude": 18.0, "best_ra": "1:35:48.22", "best_dec": "10:53:56.7", "best_alt": 48.8, "sun_elongation": 157.0, "moon_elongation": 97.0, "constelation": "Pisces", "rise_time": "2025-11-10 18:14", "set_time": "2025-11-11 05:53", "motion": 0.46, "pa": 232.0, "trend": "steady"}, {"comet_type": "P", "comet_name": "341P", "comet_fullname": "341P/Gibbs", "mpc_name": "0341P", "best_time": "2025-11-10 23:13", "orbit_calc_source": 3, "magnitude": 18.4, "best_ra": "1:55:15.13", "best_dec": "12:32:12.6", "best_alt": 50.5, "sun_elongation": 162.0, "moon_elongation": 92.0, "constelation": "Aries", "rise_time": "2025-11-10 18:14", "set_time": "2025-11-11 06:22", "motion": 0.39, "pa": 258.0, "trend": "fade"}, {"comet_type": "P", "comet_name": "513P", "comet_fullname": "513P/Broughton", "mpc_name": "0513P", "best_time": "2025-11-10 23:20", "orbit_calc_source": 3, "magnitude": 18.3, "best_ra": "2:01:58.36", "best_dec": "-0:29:40.2", "best_alt": 37.4, "sun_elongation": 156.0, "moon_elongation": 96.0, "constelation": "Cetus", "rise_time": "2025-11-10 18:14", "set_time": "2025-11-11 05:20", "motion": 0.43, "pa": 292.0, "trend": "fade"}, {"comet_type": "P", "comet_name": "82P", "comet_fullname": "82P/Gehrels", "mpc_name": "0082P", "best_time": "2025-11-11 00:39", "orbit_calc_source": 3, "magnitude": 18.8, "best_ra": "3:21:42.48", "best_dec": "18:41:40.8", "best_alt": 56.6, "sun_elongation": 176.0, "moon_elongation": 71.0, "constelation": "Aries", "rise_time": "2025-11-10 18:14", "set_time": "2025-11-11 06:33", "motion": 0.43, "pa": 254.0, "trend": "steady"}, {"comet_type": "C", "comet_name": "C/2022 N2", "comet_fullname": "C/2022 N2 (PANSTARRS)", "mpc_name": "CK22N020", "best_time": "2025-11-11 00:45", "orbit_calc_source": 0, "magnitude": 14.0, "best_ra": "3:27:15.39", "best_dec": "26:22:14.9", "best_alt": 64.3, "sun_elongation": 170.0, "moon_elongation": 68.0, "constelation": "Aries", "rise_time": "2025-11-10 18:14", "set_time": "2025-11-11 06:33", "motion": 0.26, "pa": 257.0, "trend": "steady"}, {"comet_type": "C", "comet_name": "C/2025 Q3", "comet_fullname": "C/2025 Q3 (ATLAS)", "mpc_name": "CK25Q030", "best_time": "2025-11-11 00:46", "orbit_calc_source": 3, "magnitude": 16.9, "best_ra": "3:28:31.33", "best_dec": "27:53:38.1", "best_alt": 65.8, "sun_elongation": 168.0, "moon_elongation": 67.0, "constelation": "Aries", "rise_time": "2025-11-10 18:14", "set_time": "2025-11-11 06:33", "motion": 2.14, "pa": 217.0, "trend": "bright"}, {"comet_type": "P", "comet_name": "48P", "comet_fullname": "48P/Johnson", "mpc_name": "0048P", "best_time": "2025-11-11 00:56", "orbit_calc_source": 1, "magnitude": 16.5, "best_ra": "3:38:22.07", "best_dec": "2:39:14.1", "best_alt": 40.6, "sun_elongation": 163.0, "moon_elongation": 73.0, "constelation": "Taurus", "rise_time": "2025-11-10 18:40", "set_time": "2025-11-11 06:33", "motion": 0.58, "pa": 268.0, "trend": "fade"}, {"comet_type": "P", "comet_name": "240P", "comet_fullname": "240P/NEAT", "mpc_name": "0240P", "best_time": "2025-11-11 01:18", "orbit_calc_source": 0, "magnitude": 13.0, "best_ra": "4:00:44.07", "best_dec": "4:00:58.1", "best_alt": 41.9, "sun_elongation": 161.0, "moon_elongation": 68.0, "constelation": "Taurus", "rise_time": "2025-11-10 18:55", "set_time": "2025-11-11 06:33", "motion": 0.76, "pa": 305.0, "trend": "bright"}, {"comet_type": "P", "comet_name": "123P", "comet_fullname": "123P/West-Hartley", "mpc_name": "0123P", "best_time": "2025-11-11 01:26", "orbit_calc_source": 3, "magnitude": 18.0, "best_ra": "4:08:34.65", "best_dec": "26:27:44.9", "best_alt": 64.4, "sun_elongation": 163.0, "moon_elongation": 59.0, "constelation": "Taurus", "rise_time": "2025-11-10 18:14", "set_time": "2025-11-11 06:33", "motion": 0.51, "pa": 282.0, "trend": "bright"}, {"comet_type": "N", "comet_name": "P/2004 V5-B", "comet_fullname": "P/2004 V5-B (LINEAR-Hill)", "mpc_name": "PK04V05b", "best_time": "2025-11-11 01:42", "orbit_calc_source": 3, "magnitude": 18.7, "best_ra": "4:24:13.83", "best_dec": "28:54:39.8", "best_alt": 66.8, "sun_elongation": 159.0, "moon_elongation": 56.0, "constelation": "Taurus", "rise_time": "2025-11-10 18:14", "set_time": "2025-11-11 06:33", "motion": 0.29, "pa": 281.0, "trend": "steady"}, {"comet_type": "N", "comet_name": "P/2004 V5", "comet_fullname": "P/2004 V5 (LINEAR-Hill)", "mpc_name": "PK04V050", "best_time": "2025-11-11 01:42", "orbit_calc_source": 3, "magnitude": 18.7, "best_ra": "4:24:36.28", "best_dec": "28:57:12.8", "best_alt": 66.9, "sun_elongation": 159.0, "moon_elongation": 56.0, "constelation": "Taurus", "rise_time": "2025-11-10 18:14", "set_time": "2025-11-11 06:33", "motion": 0.29, "pa": 281.0, "trend": "steady"}, {"comet_type": "P", "comet_name": "136P", "comet_fullname": "136P/Mueller", "mpc_name": "0136P", "best_time": "2025-11-11 02:09", "orbit_calc_source": 3, "magnitude": 18.2, "best_ra": "4:52:10.26", "best_dec": "10:06:04.1", "best_alt": 48.0, "sun_elongation": 153.0, "moon_elongation": 54.0, "constelation": "Orion", "rise_time": "2025-11-10 19:14", "set_time": "2025-11-11 06:33", "motion": 0.38, "pa": 258.0, "trend": "steady"}, {"comet_type": "N", "comet_name": "P/2005 SB216", "comet_fullname": "P/2005 SB216 (LONEOS)", "mpc_name": "PK05SL6B", "best_time": "2025-11-11 02:29", "orbit_calc_source": 3, "magnitude": 17.4, "best_ra": "5:12:03.25", "best_dec": "52:30:12.6", "best_alt": 89.6, "sun_elongation": 137.0, "moon_elongation": 49.0, "constelation": "Auriga", "rise_time": "2025-11-10 18:14", "set_time": "2025-11-11 06:33", "motion": 0.32, "pa": 315.0, "trend": "steady"}, {"comet_type": "P", "comet_name": "493P", "comet_fullname": "493P/LONEOS", "mpc_name": "0493P", "best_time": "2025-11-11 02:29", "orbit_calc_source": 3, "magnitude": 17.4, "best_ra": "5:12:11.73", "best_dec": "52:30:03.3", "best_alt": 89.6, "sun_elongation": 137.0, "moon_elongation": 49.0, "constelation": "Auriga", "rise_time": "2025-11-10 18:14", "set_time": "2025-11-11 06:33", "motion": 0.32, "pa": 315.0, "trend": "steady"}, {"comet_type": "P", "comet_name": "509P", "comet_fullname": "509P/Catalina", "mpc_name": "0509P", "best_time": "2025-11-11 02:45", "orbit_calc_source": 3, "magnitude": 18.1, "best_ra": "5:28:17.64", "best_dec": "27:16:56.9", "best_alt": 65.2, "sun_elongation": 146.0, "moon_elongation": 42.0, "constelation": "Taurus", "rise_time": "2025-11-10 18:14", "set_time": "2025-11-11 06:33", "motion": 0.21, "pa": 254.0, "trend": "bright"}, {"comet_type": "N", "comet_name": "P/1999 XN120", "comet_fullname": "P/1999 XN120 (Catalina)", "mpc_name": "PJ99XC0N", "best_time": "2025-11-11 03:25", "orbit_calc_source": 3, "magnitude": 18.1, "best_ra": "6:07:37.13", "best_dec": "26:18:18.4", "best_alt": 64.2, "sun_elongation": 137.0, "moon_elongation": 34.0, "constelation": "Gemini", "rise_time": "2025-11-10 18:43", "set_time": "2025-11-11 06:33", "motion": 0.16, "pa": 264.0, "trend": "bright"}, {"comet_type": "C", "comet_name": "C/2017 K2", "comet_fullname": "C/2017 K2 (PANSTARRS)", "mpc_name": "CK17K020", "best_time": "2025-11-11 03:30", "orbit_calc_source": 1, "magnitude": 17.7, "best_ra": "6:12:52.15", "best_dec": "29:42:56.3", "best_alt": 67.6, "sun_elongation": 136.0, "moon_elongation": 33.0, "constelation": "Auriga", "rise_time": "2025-11-10 18:17", "set_time": "2025-11-11 06:33", "motion": 0.22, "pa": 290.0, "trend": "steady"}, {"comet_type": "C", "comet_name": "C/2022 L2", "comet_fullname": "C/2022 L2 (ATLAS)", "mpc_name": "CK22L020", "best_time": "2025-11-11 03:43", "orbit_calc_source": 3, "magnitude": 18.3, "best_ra": "6:25:38.53", "best_dec": "-24:25:00.1", "best_alt": 13.6, "sun_elongation": 116.0, "moon_elongation": 56.0, "constelation": "Canis Major", "rise_time": "2025-11-11 00:01", "set_time": "2025-11-11 06:33", "motion": 0.48, "pa": 254.0, "trend": "steady"}, {"comet_type": "P", "comet_name": "233P", "comet_fullname": "233P/La Sagra", "mpc_name": "0233P", "best_time": "2025-11-11 03:53", "orbit_calc_source": 3, "magnitude": 17.7, "best_ra": "6:36:28.54", "best_dec": "22:49:33.3", "best_alt": 60.7, "sun_elongation": 131.0, "moon_elongation": 28.0, "constelation": "Gemini", "rise_time": "2025-11-10 19:39", "set_time": "2025-11-11 06:33", "motion": 0.52, "pa": 45.0, "trend": "bright"}, {"comet_type": "P", "comet_name": "248P", "comet_fullname": "248P/Gibbs", "mpc_name": "0248P", "best_time": "2025-11-11 04:02", "orbit_calc_source": 3, "magnitude": 18.3, "best_ra": "6:44:54.96", "best_dec": "15:26:12.3", "best_alt": 53.4, "sun_elongation": 128.0, "moon_elongation": 27.0, "constelation": "Gemini", "rise_time": "2025-11-10 20:36", "set_time": "2025-11-11 06:33", "motion": 0.26, "pa": 143.0, "trend": "steady"}, {"comet_type": "P", "comet_name": "183P", "comet_fullname": "183P/Korlevic-Juric", "mpc_name": "0183P", "best_time": "2025-11-11 04:12", "orbit_calc_source": 3, "magnitude": 18.8, "best_ra": "6:55:20.37", "best_dec": "44:50:52.7", "best_alt": 82.8, "sun_elongation": 125.0, "moon_elongation": 31.0, "constelation": "Auriga", "rise_time": "2025-11-10 18:14", "set_time": "2025-11-11 06:33", "motion": 0.2, "pa": 333.0, "trend": "bright"}, {"comet_type": "P", "comet_name": "198P", "comet_fullname": "198P/ODAS", "mpc_name": "0198P", "best_time": "2025-11-11 04:33", "orbit_calc_source": 3, "magnitude": 16.1, "best_ra": "7:15:45.90", "best_dec": "24:22:03.7", "best_alt": 62.3, "sun_elongation": 122.0, "moon_elongation": 19.0, "constelation": "Gemini", "rise_time": "2025-11-10 20:07", "set_time": "2025-11-11 06:33", "motion": 0.35, "pa": 92.0, "trend": "bright"}, {"comet_type": "P", "comet_name": "74P", "comet_fullname": "74P/Smirnova-Chernykh", "mpc_name": "0074P", "best_time": "2025-11-11 04:37", "orbit_calc_source": 3, "magnitude": 18.4, "best_ra": "7:20:32.16", "best_dec": "27:06:17.2", "best_alt": 65.0, "sun_elongation": 121.0, "moon_elongation": 18.0, "constelation": "Gemini", "rise_time": "2025-11-10 19:49", "set_time": "2025-11-11 06:33", "motion": 0.07, "pa": 328.0, "trend": "steady"}, {"comet_type": "N", "comet_name": "P/2004 V5-A", "comet_fullname": "P/2004 V5-A (LINEAR-Hill)", "mpc_name": "PK04V05a", "best_time": "2025-11-11 04:41", "orbit_calc_source": 3, "magnitude": 18.0, "best_ra": "7:23:55.08", "best_dec": "40:26:39.0", "best_alt": 78.4, "sun_elongation": 121.0, "moon_elongation": 24.0, "constelation": "Auriga", "rise_time": "2025-11-10 18:14", "set_time": "2025-11-11 06:33", "motion": 0.2, "pa": 4.0, "trend": "bright"}, {"comet_type": "P", "comet_name": "186P", "comet_fullname": "186P/Garradd", "mpc_name": "0186P", "best_time": "2025-11-11 05:08", "orbit_calc_source": 3, "magnitude": 18.1, "best_ra": "7:51:24.13", "best_dec": "45:02:32.1", "best_alt": 83.0, "sun_elongation": 115.0, "moon_elongation": 25.0, "constelation": "Lynx", "rise_time": "2025-11-10 18:14", "set_time": "2025-11-11 06:33", "motion": 0.11, "pa": 341.0, "trend": "steady"}, {"comet_type": "P", "comet_name": "450P", "comet_fullname": "450P/LONEOS", "mpc_name": "0450P", "best_time": "2025-11-11 05:20", "orbit_calc_source": 3, "magnitude": 17.7, "best_ra": "8:03:29.96", "best_dec": "17:25:39.0", "best_alt": 55.3, "sun_elongation": 110.0, "moon_elongation": 9.0, "constelation": "Cancer", "rise_time": "2025-11-10 21:42", "set_time": "2025-11-11 06:33", "motion": 0.05, "pa": 81.0, "trend": "steady"}, {"comet_type": "P", "comet_name": "242P", "comet_fullname": "242P/Spahr", "mpc_name": "0242P", "best_time": "2025-11-11 05:25", "orbit_calc_source": 3, "magnitude": 17.2, "best_ra": "8:07:49.48", "best_dec": "-13:35:04.4", "best_alt": 24.4, "sun_elongation": 99.0, "moon_elongation": 36.0, "constelation": "Puppis", "rise_time": "2025-11-11 00:34", "set_time": "2025-11-11 06:33", "motion": 0.27, "pa": 159.0, "trend": "steady"}, {"comet_type": "P", "comet_name": "24P", "comet_fullname": "24P/Schaumasse", "mpc_name": "0024P", "best_time": "2025-11-11 06:06", "orbit_calc_source": 3, "magnitude": 11.3, "best_ra": "8:49:48.16", "best_dec": "20:05:58.3", "best_alt": 58.0, "sun_elongation": 100.0, "moon_elongation": 3.0, "constelation": "Cancer", "rise_time": "2025-11-10 22:10", "set_time": "2025-11-11 06:33", "motion": 2.41, "pa": 91.0, "trend": "bright"}, {"comet_type": "C", "comet_name": "C/2024 A1", "comet_fullname": "C/2024 A1 (ATLAS)", "mpc_name": "CK24A010", "best_time": "2025-11-11 06:14", "orbit_calc_source": 1, "magnitude": 16.6, "best_ra": "8:57:36.42", "best_dec": "39:45:38.5", "best_alt": 77.7, "sun_elongation": 103.0, "moon_elongation": 19.0, "constelation": "Lynx", "rise_time": "2025-11-10 18:14", "set_time": "2025-11-11 06:33", "motion": 0.71, "pa": 1.0, "trend": "steady"}, {"comet_type": "C", "comet_name": "C/2022 R6", "comet_fullname": "C/2022 R6 (PANSTARRS)", "mpc_name": "CK22R060", "best_time": "2025-11-11 06:15", "orbit_calc_source": 1, "magnitude": 16.4, "best_ra": "8:58:12.24", "best_dec": "-12:03:04.4", "best_alt": 25.9, "sun_elongation": 88.0, "moon_elongation": 34.0, "constelation": "Hydra", "rise_time": "2025-11-11 01:15", "set_time": "2025-11-11 06:33", "motion": 0.12, "pa": 111.0, "trend": "steady"}, {"comet_type": "P", "comet_name": "217P", "comet_fullname": "217P/LINEAR", "mpc_name": "0217P", "best_time": "2025-11-11 06:30", "orbit_calc_source": 1, "magnitude": 16.8, "best_ra": "9:13:33.81", "best_dec": "12:17:51.9", "best_alt": 50.2, "sun_elongation": 92.0, "moon_elongation": 12.0, "constelation": "Cancer", "rise_time": "2025-11-10 23:22", "set_time": "2025-11-11 06:33", "motion": 0.36, "pa": 91.0, "trend": "fade"}, {"comet_type": "C", "comet_name": "C/2022 QE78", "comet_fullname": "C/2022 QE78 (ATLAS)", "mpc_name": "CK22Q78E", "best_time": "2025-11-11 06:33", "orbit_calc_source": 1, "magnitude": 15.3, "best_ra": "9:21:01.98", "best_dec": "20:05:25.0", "best_alt": 58.0, "sun_elongation": 93.0, "moon_elongation": 10.0, "constelation": "Cancer", "rise_time": "2025-11-10 22:42", "set_time": "2025-11-11 06:33", "motion": 0.27, "pa": 62.0, "trend": "steady"}, {"comet_type": "P", "comet_name": "124P", "comet_fullname": "124P/Mrkos", "mpc_name": "0124P", "best_time": "2025-11-11 06:33", "orbit_calc_source": 3, "magnitude": 18.0, "best_ra": "9:23:52.42", "best_dec": "55:23:22.2", "best_alt": 86.5, "sun_elongation": 102.0, "moon_elongation": 35.0, "constelation": "Ursa Major", "rise_time": "2025-11-10 18:14", "set_time": "2025-11-11 06:33", "motion": 0.63, "pa": 67.0, "trend": "bright"}, {"comet_type": "C", "comet_name": "C/2024 X2", "comet_fullname": "C/2024 X2 (ATLAS)", "mpc_name": "CK24X020", "best_time": "2025-11-11 06:33", "orbit_calc_source": 3, "magnitude": 18.3, "best_ra": "9:25:50.19", "best_dec": "-5:14:35.4", "best_alt": 32.7, "sun_elongation": 84.0, "moon_elongation": 29.0, "constelation": "Hydra", "rise_time": "2025-11-11 01:07", "set_time": "2025-11-11 06:33", "motion": 0.24, "pa": 340.0, "trend": "steady"}, {"comet_type": "C", "comet_name": "C/2025 D1", "comet_fullname": "C/2025 D1 (Groeller)", "mpc_name": "CK25D010", "best_time": "2025-11-11 06:33", "orbit_calc_source": 3, "magnitude": 18.7, "best_ra": "9:36:33.20", "best_dec": "32:56:59.9", "best_alt": 70.5, "sun_elongation": 93.0, "moon_elongation": 17.0, "constelation": "Leo Minor", "rise_time": "2025-11-10 21:01", "set_time": "2025-11-11 06:33", "motion": 0.01, "pa": 240.0, "trend": "steady"}, {"comet_type": "P", "comet_name": "195P", "comet_fullname": "195P/Hill", "mpc_name": "0195P", "best_time": "2025-11-11 06:33", "orbit_calc_source": 3, "magnitude": 18.3, "best_ra": "9:48:27.33", "best_dec": "-23:40:08.8", "best_alt": 14.0, "sun_elongation": 74.0, "moon_elongation": 48.0, "constelation": "Hydra", "rise_time": "2025-11-11 03:18", "set_time": "2025-11-11 06:33", "motion": 0.53, "pa": 145.0, "trend": "steady"}, {"comet_type": "P", "comet_name": "171P", "comet_fullname": "171P/Spahr", "mpc_name": "0171P", "best_time": "2025-11-11 06:33", "orbit_calc_source": 3, "magnitude": 17.2, "best_ra": "9:55:42.36", "best_dec": "17:25:15.7", "best_alt": 54.5, "sun_elongation": 84.0, "moon_elongation": 18.0, "constelation": "Leo", "rise_time": "2025-11-10 23:34", "set_time": "2025-11-11 06:33", "motion": 1.23, "pa": 83.0, "trend": "steady"}, {"comet_type": "P", "comet_name": "21P", "comet_fullname": "21P/Giacobini-Zinner", "mpc_name": "0021P", "best_time": "2025-11-11 06:33", "orbit_calc_source": 3, "magnitude": 18.1, "best_ra": "9:56:23.31", "best_dec": "-16:40:34.2", "best_alt": 20.7, "sun_elongation": 74.0, "moon_elongation": 42.0, "constelation": "Hydra", "rise_time": "2025-11-11 02:40", "set_time": "2025-11-11 06:33", "motion": 0.51, "pa": 139.0, "trend": "fade"}, {"comet_type": "P", "comet_name": "472P", "comet_fullname": "472P/NEAT-LINEAR", "mpc_name": "0472P", "best_time": "2025-11-11 06:33", "orbit_calc_source": 1, "magnitude": 17.8, "best_ra": "10:08:06.74", "best_dec": "1:19:56.4", "best_alt": 38.1, "sun_elongation": 76.0, "moon_elongation": 29.0, "constelation": "Sextans", "rise_time": "2025-11-11 01:15", "set_time": "2025-11-11 06:33", "motion": 0.34, "pa": 120.0, "trend": "steady"}, {"comet_type": "P", "comet_name": "489P", "comet_fullname": "489P/Denning", "mpc_name": "0489P", "best_time": "2025-11-11 06:33", "orbit_calc_source": 3, "magnitude": 18.4, "best_ra": "10:26:19.12", "best_dec": "14:20:27.1", "best_alt": 49.7, "sun_elongation": 76.0, "moon_elongation": 26.0, "constelation": "Leo", "rise_time": "2025-11-11 00:22", "set_time": "2025-11-11 06:33", "motion": 1.79, "pa": 111.0, "trend": "bright"}, {"comet_type": "P", "comet_name": "187P", "comet_fullname": "187P/LINEAR", "mpc_name": "0187P", "best_time": "2025-11-11 06:33", "orbit_calc_source": 3, "magnitude": 19.0, "best_ra": "10:28:59.68", "best_dec": "16:49:48.5", "best_alt": 51.9, "sun_elongation": 76.0, "moon_elongation": 26.0, "constelation": "Leo", "rise_time": "2025-11-11 00:11", "set_time": "2025-11-11 06:33", "motion": 0.37, "pa": 96.0, "trend": "bright"}, {"comet_type": "P", "comet_name": "43P", "comet_fullname": "43P/Wolf-Harrington", "mpc_name": "0043P", "best_time": "2025-11-11 06:33", "orbit_calc_source": 1, "magnitude": 16.2, "best_ra": "10:30:55.91", "best_dec": "0:17:25.7", "best_alt": 35.9, "sun_elongation": 70.0, "moon_elongation": 34.0, "constelation": "Sextans", "rise_time": "2025-11-11 01:43", "set_time": "2025-11-11 06:33", "motion": 0.89, "pa": 120.0, "trend": "steady"}, {"comet_type": "C", "comet_name": "C/2023 X2", "comet_fullname": "C/2023 X2 (Lemmon)", "mpc_name": "CK23X020", "best_time": "2025-11-11 06:33", "orbit_calc_source": 3, "magnitude": 17.6, "best_ra": "10:41:06.77", "best_dec": "83:23:37.1", "best_alt": 58.2, "sun_elongation": 105.0, "moon_elongation": 63.0, "constelation": "Camelopardalis", "rise_time": "2025-11-10 18:14", "set_time": "2025-11-11 06:33", "motion": 0.64, "pa": 48.0, "trend": "steady"}, {"comet_type": "P", "comet_name": "164P", "comet_fullname": "164P/Christensen", "mpc_name": "0164P", "best_time": "2025-11-11 06:33", "orbit_calc_source": 3, "magnitude": 16.4, "best_ra": "10:41:29.69", "best_dec": "19:39:20.8", "best_alt": 53.6, "sun_elongation": 75.0, "moon_elongation": 28.0, "constelation": "Leo", "rise_time": "2025-11-11 00:05", "set_time": "2025-11-11 06:33", "motion": 0.84, "pa": 92.0, "trend": "steady"}, {"comet_type": "C", "comet_name": "C/2023 F3", "comet_fullname": "C/2023 F3 (ATLAS)", "mpc_name": "CK23F030", "best_time": "2025-11-11 06:33", "orbit_calc_source": 3, "magnitude": 17.4, "best_ra": "11:04:20.33", "best_dec": "-23:52:23.5", "best_alt": 10.5, "sun_elongation": 57.0, "moon_elongation": 57.0, "constelation": "Crater", "rise_time": "2025-11-11 04:35", "set_time": "2025-11-11 06:33", "motion": 0.1, "pa": 199.0, "trend": "steady"}, {"comet_type": "C", "comet_name": "C/2025 J1", "comet_fullname": "C/2025 J1 (Borisov)", "mpc_name": "CK25J010", "best_time": "2025-11-11 06:33", "orbit_calc_source": 3, "magnitude": 18.1, "best_ra": "11:18:26.31", "best_dec": "72:17:30.5", "best_alt": 65.9, "sun_elongation": 97.0, "moon_elongation": 56.0, "constelation": "Ursa Major", "rise_time": "2025-11-10 18:14", "set_time": "2025-11-11 06:33", "motion": 0.37, "pa": 345.0, "trend": "bright"}, {"comet_type": "C", "comet_name": "C/2025 K1", "comet_fullname": "C/2025 K1 (ATLAS)", "mpc_name": "CK25K010", "best_time": "2025-11-11 06:33", "orbit_calc_source": 0, "magnitude": 9.9, "best_ra": "11:21:36.14", "best_dec": "20:07:27.8", "best_alt": 49.8, "sun_elongation": 67.0, "moon_elongation": 38.0, "constelation": "Leo", "rise_time": "2025-11-11 00:46", "set_time": "2025-11-11 06:33", "motion": 5.41, "pa": 344.0, "trend": "fade"}, {"comet_type": "P", "comet_name": "29P", "comet_fullname": "29P/Schwassmann-Wachmann", "mpc_name": "0029P", "best_time": "2025-11-11 06:33", "orbit_calc_source": 1, "magnitude": 12.7, "best_ra": "11:22:11.04", "best_dec": "-0:51:54.2", "best_alt": 30.8, "sun_elongation": 58.0, "moon_elongation": 45.0, "constelation": "Leo", "rise_time": "2025-11-11 02:40", "set_time": "2025-11-11 06:33", "motion": 0.33, "pa": 121.0, "trend": "steady"}, {"comet_type": "C", "comet_name": "C/2024 L5", "comet_fullname": "C/2024 L5 (ATLAS)", "mpc_name": "CK24L050", "best_time": "2025-11-11 06:33", "orbit_calc_source": 1, "magnitude": 18.0, "best_ra": "11:24:29.20", "best_dec": "-0:58:16.5", "best_alt": 30.5, "sun_elongation": 57.0, "moon_elongation": 46.0, "constelation": "Leo", "rise_time": "2025-11-11 02:43", "set_time": "2025-11-11 06:33", "motion": 0.08, "pa": 315.0, "trend": "steady"}, {"comet_type": "C", "comet_name": "C/2024 G2", "comet_fullname": "C/2024 G2 (ATLAS)", "mpc_name": "CK24G020", "best_time": "2025-11-11 06:33", "orbit_calc_source": 3, "magnitude": 18.3, "best_ra": "12:07:18.86", "best_dec": "-12:42:08.5", "best_alt": 15.5, "sun_elongation": 43.0, "moon_elongation": 61.0, "constelation": "Corvus", "rise_time": "2025-11-11 04:28", "set_time": "2025-11-11 06:33", "motion": 0.21, "pa": 71.0, "trend": "steady"}, {"comet_type": "P", "comet_name": "235P", "comet_fullname": "235P/LINEAR", "mpc_name": "0235P", "best_time": "2025-11-11 06:33", "orbit_calc_source": 3, "magnitude": 17.2, "best_ra": "12:42:00.49", "best_dec": "-7:51:26.6", "best_alt": 15.8, "sun_elongation": 36.0, "moon_elongation": 66.0, "constelation": "Virgo", "rise_time": "2025-11-11 04:36", "set_time": "2025-11-11 06:33", "motion": 1.47, "pa": 109.0, "trend": "bright"}, {"comet_type": "P", "comet_name": "60P", "comet_fullname": "60P/Tsuchinshan", "mpc_name": "0060P", "best_time": "2025-11-11 06:33", "orbit_calc_source": 3, "magnitude": 18.1, "best_ra": "13:01:47.35", "best_dec": "-9:21:19.7", "best_alt": 12.0, "sun_elongation": 31.0, "moon_elongation": 71.0, "constelation": "Virgo", "rise_time": "2025-11-11 05:03", "set_time": "2025-11-11 06:33", "motion": 1.4, "pa": 113.0, "trend": "fade"}, {"comet_type": "I", "comet_name": "3I", "comet_fullname": "3I/ATLAS", "mpc_name": "0003I", "best_time": "2025-11-11 06:33", "orbit_calc_source": 1, "magnitude": 11.0, "best_ra": "13:01:51.06", "best_dec": "-4:45:26.1", "best_alt": 15.9, "sun_elongation": 33.0, "moon_elongation": 69.0, "constelation": "Virgo", "rise_time": "2025-11-11 04:40", "set_time": "2025-11-11 06:33", "motion": 1.64, "pa": 288.0, "trend": "fade"}, {"comet_type": "P", "comet_name": "40P", "comet_fullname": "40P/Vaisala", "mpc_name": "0040P", "best_time": "2025-11-11 06:33", "orbit_calc_source": 3, "magnitude": 15.4, "best_ra": "13:13:19.91", "best_dec": "-0:49:35.3", "best_alt": 17.6, "sun_elongation": 32.0, "moon_elongation": 70.0, "constelation": "Virgo", "rise_time": "2025-11-11 04:30", "set_time": "2025-11-11 06:33", "motion": 1.68, "pa": 108.0, "trend": "steady"}, {"comet_type": "N", "comet_name": "P/2023 S1", "comet_fullname": "P/2023 S1", "mpc_name": "PK23S010", "best_time": "2025-11-11 06:33", "orbit_calc_source": 1, "magnitude": 18.1, "best_ra": "13:32:49.22", "best_dec": "-16:27:32.5", "best_alt": 2.2, "sun_elongation": 22.0, "moon_elongation": 81.0, "constelation": "Virgo", "rise_time": "2025-11-11 06:14", "set_time": "2025-11-11 06:33", "motion": 0.96, "pa": 115.0, "trend": "steady"}, {"comet_type": "P", "comet_name": "10P", "comet_fullname": "10P/Tempel 2", "mpc_name": "0010P", "best_time": "2025-11-11 06:33", "orbit_calc_source": 3, "magnitude": 18.8, "best_ra": "13:58:43.91", "best_dec": "-2:32:19.3", "best_alt": 9.8, "sun_elongation": 22.0, "moon_elongation": 81.0, "constelation": "Virgo", "rise_time": "2025-11-11 05:25", "set_time": "2025-11-11 06:33", "motion": 1.03, "pa": 109.0, "trend": "bright"}, {"comet_type": "C", "comet_name": "C/2025 V1", "comet_fullname": "C/2025 V1 (Borisov)", "mpc_name": "CK25V010", "best_time": "2025-11-11 06:33", "orbit_calc_source": 3, "magnitude": 12.3, "best_ra": "14:04:41.19", "best_dec": "3:57:39.1", "best_alt": 14.1, "sun_elongation": 26.0, "moon_elongation": 80.0, "constelation": "Virgo", "rise_time": "2025-11-11 04:57", "set_time": "2025-11-11 06:33", "motion": 9.96, "pa": 76.0, "trend": "steady"}, {"comet_type": "P", "comet_name": "391P", "comet_fullname": "391P/Kowalski", "mpc_name": "0391P", "best_time": "2025-11-11 06:33", "orbit_calc_source": 3, "magnitude": 18.5, "best_ra": "14:27:58.58", "best_dec": "4:04:43.1", "best_alt": 10.7, "sun_elongation": 24.0, "moon_elongation": 86.0, "constelation": "Virgo", "rise_time": "2025-11-11 05:20", "set_time": "2025-11-11 06:33", "motion": 0.62, "pa": 106.0, "trend": "steady"}], "signature": {"source": "COBS Query API", "version": "1.2", "date": "2024 Sep"}}