{"location": {"name": "", "lat": 52.09, "long": 5.12, "tz": "Europe/Amsterdam"}, "sun events": {"Day ends": "2025-11-06 17:01 CET", "Civil twilight ends": "2025-11-06 17:37 CET", "Nautical twilight ends": "2025-11-06 18:18 CET", "Astronomical twilight ends": "2025-11-06 18:57 CET", "Astronomical twilight starts": "2025-11-07 05:49 CET", "Nautical twilight starts": "2025-11-07 06:28 CET", "Civil twilight starts": "2025-11-07 07:09 CET", "Day starts": "2025-11-07 07:45 CET"}, "moon events": {"Rise": "2025-11-06 17:00 CET", "Set": "2025-11-07 10:50 CET", "Moon phase": 96.8}, "session events": {"start_at": -12.0, "start_time": "2025-11-06 18:20 CET", "end_time": "2025-11-07 06:26 CET"}, "limits": {"mag": 19.0, "alt": 0.0, "sun_elong": 0.0, "moon_elong": 0.0}, "comet_list": [{"comet_type": "C", "comet_name": "C/2023 H5", "comet_fullname": "C/2023 H5 (Lemmon)", "mpc_name": "CK23H050", "best_time": "2025-11-06 18:20", "orbit_calc_source": 1, "magnitude": 16.7, "best_ra": "15:29:10.47", "best_dec": "63:21:47.6", "best_alt": 49.3, "sun_elongation": 80.0, "moon_elongation": 92.0, "constelation": "Draco", "rise_time": "2025-11-06 18:20", "set_time": "2025-11-07 06:26", "motion": 0.88, "pa": 90.0, "trend": "steady"}, {"comet_type": "C", "comet_name": "C/2025 T1", "comet_fullname": "C/2025 T1 (ATLAS)", "mpc_name": "CK25T010", "best_time": "2025-11-06 18:20", "orbit_calc_source": 0, "magnitude": 11.1, "best_ra": "15:32:43.21", "best_dec": "53:31:03.7", "best_alt": 45.2, "sun_elongation": 70.0, "moon_elongation": 102.0, "constelation": "Draco", "rise_time": "2025-11-06 18:20", "set_time": "2025-11-07 06:26", "motion": 5.19, "pa": 106.0, "trend": "bright"}, {"comet_type": "C", "comet_name": "C/2024 G6", "comet_fullname": "C/2024 G6 (ATLAS)", "mpc_name": "CK24G060", "best_time": "2025-11-06 18:20", "orbit_calc_source": 3, "magnitude": 17.9, "best_ra": "16:05:35.85", "best_dec": "-9:49:16.7", "best_alt": 4.4, "sun_elongation": 20.0, "moon_elongation": 165.0, "constelation": "Scorpius", "rise_time": "2025-11-06 18:20", "set_time": "2025-11-06 18:52", "motion": 0.26, "pa": 69.0, "trend": "steady"}, {"comet_type": "C", "comet_name": "C/2021 G2", "comet_fullname": "C/2021 G2 (Atlas)", "mpc_name": "CK21G020", "best_time": "2025-11-06 18:20", "orbit_calc_source": 1, "magnitude": 14.9, "best_ra": "16:07:00.16", "best_dec": "-1:19:53.8", "best_alt": 11.4, "sun_elongation": 24.0, "moon_elongation": 157.0, "constelation": "Serpens Caput", "rise_time": "2025-11-06 18:20", "set_time": "2025-11-06 19:38", "motion": 0.5, "pa": 89.0, "trend": "steady"}, {"comet_type": "C", "comet_name": "C/2025 A6", "comet_fullname": "C/2025 A6 (Lemmon)", "mpc_name": "CK25A060", "best_time": "2025-11-06 18:20", "orbit_calc_source": 0, "magnitude": 4.5, "best_ra": "16:51:56.32", "best_dec": "-7:08:32.0", "best_alt": 12.9, "sun_elongation": 32.0, "moon_elongation": 158.0, "constelation": "Ophiuchus", "rise_time": "2025-11-06 18:20", "set_time": "2025-11-06 19:52", "motion": 4.13, "pa": 150.0, "trend": "fade"}, {"comet_type": "C", "comet_name": "C/2024 E1", "comet_fullname": "C/2024 E1 (Wierzchos)", "mpc_name": "CK24E010", "best_time": "2025-11-06 18:20", "orbit_calc_source": 0, "magnitude": 12.6, "best_ra": "16:57:21.84", "best_dec": "5:20:41.5", "best_alt": 24.0, "sun_elongation": 39.0, "moon_elongation": 147.0, "constelation": "Ophiuchus", "rise_time": "2025-11-06 18:20", "set_time": "2025-11-06 21:02", "motion": 1.57, "pa": 142.0, "trend": "bright"}, {"comet_type": "C", "comet_name": "C/2024 N3", "comet_fullname": "C/2024 N3 (Sarneczky)", "mpc_name": "CK24N030", "best_time": "2025-11-06 18:20", "orbit_calc_source": 3, "magnitude": 19.0, "best_ra": "17:05:36.27", "best_dec": "37:20:03.7", "best_alt": 49.4, "sun_elongation": 63.0, "moon_elongation": 116.0, "constelation": "Hercules", "rise_time": "2025-11-06 18:20", "set_time": "2025-11-07 06:26", "motion": 0.62, "pa": 141.0, "trend": "steady"}, {"comet_type": "P", "comet_name": "141P-B", "comet_fullname": "141P-B/Machholz", "mpc_name": "141P-B", "best_time": "2025-11-06 18:20", "orbit_calc_source": 3, "magnitude": 14.8, "best_ra": "17:21:26.06", "best_dec": "-14:06:03.7", "best_alt": 10.6, "sun_elongation": 37.0, "moon_elongation": 157.0, "constelation": "Serpens Cauda", "rise_time": "2025-11-06 18:20", "set_time": "2025-11-06 19:44", "motion": 1.0, "pa": 102.0, "trend": "bright"}, {"comet_type": "C", "comet_name": "C/2024 G4", "comet_fullname": "C/2024 G4 (PANSTARRS)", "mpc_name": "CK24G040", "best_time": "2025-11-06 18:20", "orbit_calc_source": 3, "magnitude": 18.8, "best_ra": "17:36:29.71", "best_dec": "2:48:23.6", "best_alt": 27.1, "sun_elongation": 46.0, "moon_elongation": 143.0, "constelation": "Ophiuchus", "rise_time": "2025-11-06 18:20", "set_time": "2025-11-06 21:28", "motion": 0.63, "pa": 109.0, "trend": "steady"}, {"comet_type": "C", "comet_name": "C/2023 A3", "comet_fullname": "C/2023 A3 (Tsuchinshan-ATLAS)", "mpc_name": "CK23A030", "best_time": "2025-11-06 18:20", "orbit_calc_source": 1, "magnitude": 17.6, "best_ra": "18:05:36.05", "best_dec": "13:16:07.2", "best_alt": 39.8, "sun_elongation": 57.0, "moon_elongation": 131.0, "constelation": "Ophiuchus", "rise_time": "2025-11-06 18:20", "set_time": "2025-11-06 22:54", "motion": 0.3, "pa": 124.0, "trend": "fade"}, {"comet_type": "C", "comet_name": "C/2025 R1", "comet_fullname": "C/2025 R1 (ATLAS)", "mpc_name": "CK25R010", "best_time": "2025-11-06 18:20", "orbit_calc_source": 3, "magnitude": 18.2, "best_ra": "18:41:17.65", "best_dec": "53:26:15.5", "best_alt": 71.3, "sun_elongation": 86.0, "moon_elongation": 94.0, "constelation": "Draco", "rise_time": "2025-11-06 18:20", "set_time": "2025-11-07 06:26", "motion": 2.09, "pa": 178.0, "trend": "fade"}, {"comet_type": "C", "comet_name": "C/2024 J3", "comet_fullname": "C/2024 J3 (ATLAS)", "mpc_name": "CK24J030", "best_time": "2025-11-06 18:20", "orbit_calc_source": 1, "magnitude": 15.6, "best_ra": "18:41:51.17", "best_dec": "-9:00:26.0", "best_alt": 23.4, "sun_elongation": 57.0, "moon_elongation": 137.0, "constelation": "Scutum", "rise_time": "2025-11-06 18:20", "set_time": "2025-11-06 21:33", "motion": 0.32, "pa": 58.0, "trend": "steady"}, {"comet_type": "C", "comet_name": "C/2023 R1", "comet_fullname": "C/2023 R1 (PANSTARRS)", "mpc_name": "CK23R010", "best_time": "2025-11-06 18:20", "orbit_calc_source": 1, "magnitude": 15.9, "best_ra": "19:14:48.38", "best_dec": "4:03:43.5", "best_alt": 38.4, "sun_elongation": 69.0, "moon_elongation": 124.0, "constelation": "Aquila", "rise_time": "2025-11-06 18:20", "set_time": "2025-11-06 23:13", "motion": 0.42, "pa": 194.0, "trend": "steady"}, {"comet_type": "P", "comet_name": "65P", "comet_fullname": "65P/Gunn", "mpc_name": "0065P", "best_time": "2025-11-06 18:20", "orbit_calc_source": 1, "magnitude": 17.2, "best_ra": "19:27:46.23", "best_dec": "-29:33:20.1", "best_alt": 6.7, "sun_elongation": 65.0, "moon_elongation": 133.0, "constelation": "Sagittarius", "rise_time": "2025-11-06 18:20", "set_time": "2025-11-06 20:01", "motion": 0.79, "pa": 79.0, "trend": "fade"}, {"comet_type": "P", "comet_name": "491P", "comet_fullname": "491P/Spacewatch-PANSTARRS", "mpc_name": "0491P", "best_time": "2025-11-06 18:20", "orbit_calc_source": 3, "magnitude": 18.9, "best_ra": "20:02:51.72", "best_dec": "-20:28:34.3", "best_alt": 16.9, "sun_elongation": 74.0, "moon_elongation": 123.0, "constelation": "Sagittarius", "rise_time": "2025-11-06 18:20", "set_time": "2025-11-06 21:47", "motion": 0.46, "pa": 72.0, "trend": "fade"}, {"comet_type": "N", "comet_name": "P/1996 R2", "comet_fullname": "P/1996 R2 (Lagerkvist)", "mpc_name": "PJ96R020", "best_time": "2025-11-06 18:20", "orbit_calc_source": 3, "magnitude": 18.5, "best_ra": "20:06:39.16", "best_dec": "-22:47:54.1", "best_alt": 14.7, "sun_elongation": 74.0, "moon_elongation": 123.0, "constelation": "Sagittarius", "rise_time": "2025-11-06 18:20", "set_time": "2025-11-06 21:35", "motion": 0.69, "pa": 75.0, "trend": "steady"}, {"comet_type": "P", "comet_name": "502P", "comet_fullname": "502P/NEAT", "mpc_name": "0502P", "best_time": "2025-11-06 18:20", "orbit_calc_source": 3, "magnitude": 18.0, "best_ra": "20:07:32.96", "best_dec": "-11:27:27.7", "best_alt": 26.0, "sun_elongation": 77.0, "moon_elongation": 119.0, "constelation": "Aquila", "rise_time": "2025-11-06 18:20", "set_time": "2025-11-06 22:45", "motion": 0.45, "pa": 81.0, "trend": "fade"}, {"comet_type": "P", "comet_name": "78P", "comet_fullname": "78P/Gehrels", "mpc_name": "0078P", "best_time": "2025-11-06 18:20", "orbit_calc_source": 1, "magnitude": 16.9, "best_ra": "20:19:49.43", "best_dec": "-13:42:28.7", "best_alt": 24.0, "sun_elongation": 80.0, "moon_elongation": 117.0, "constelation": "Capricornus", "rise_time": "2025-11-06 18:20", "set_time": "2025-11-06 22:45", "motion": 0.64, "pa": 85.0, "trend": "bright"}, {"comet_type": "P", "comet_name": "261P", "comet_fullname": "261P/Larson", "mpc_name": "0261P", "best_time": "2025-11-06 18:20", "orbit_calc_source": 3, "magnitude": 18.5, "best_ra": "20:41:22.53", "best_dec": "-13:19:13.5", "best_alt": 24.6, "sun_elongation": 85.0, "moon_elongation": 112.0, "constelation": "Aquarius", "rise_time": "2025-11-06 18:20", "set_time": "2025-11-06 23:08", "motion": 1.01, "pa": 74.0, "trend": "steady"}, {"comet_type": "P", "comet_name": "93P", "comet_fullname": "93P/Lovas", "mpc_name": "0093P", "best_time": "2025-11-06 18:36", "orbit_calc_source": 3, "magnitude": 17.0, "best_ra": "21:02:07.23", "best_dec": "-17:35:02.6", "best_alt": 20.4, "sun_elongation": 88.0, "moon_elongation": 109.0, "constelation": "Capricornus", "rise_time": "2025-11-06 18:20", "set_time": "2025-11-06 23:04", "motion": 0.57, "pa": 56.0, "trend": "bright"}, {"comet_type": "P", "comet_name": "243P", "comet_fullname": "243P/NEAT", "mpc_name": "0243P", "best_time": "2025-11-06 18:59", "orbit_calc_source": 3, "magnitude": 18.4, "best_ra": "21:24:58.64", "best_dec": "-23:33:42.4", "best_alt": 14.4, "sun_elongation": 92.0, "moon_elongation": 106.0, "constelation": "Capricornus", "rise_time": "2025-11-06 18:20", "set_time": "2025-11-06 22:47", "motion": 0.63, "pa": 65.0, "trend": "steady"}, {"comet_type": "P", "comet_name": "362P", "comet_fullname": "362P/Spacewatch", "mpc_name": "0362P", "best_time": "2025-11-06 19:01", "orbit_calc_source": 3, "magnitude": 18.4, "best_ra": "21:26:30.53", "best_dec": "-4:49:22.3", "best_alt": 33.1, "sun_elongation": 98.0, "moon_elongation": 99.0, "constelation": "Aquarius", "rise_time": "2025-11-06 18:20", "set_time": "2025-11-07 00:39", "motion": 0.34, "pa": 104.0, "trend": "fade"}, {"comet_type": "N", "comet_name": "P/1999 RO28", "comet_fullname": "P/1999 RO28 (LONEOS)", "mpc_name": "PJ99R28O", "best_time": "2025-11-06 19:03", "orbit_calc_source": 3, "magnitude": 18.9, "best_ra": "21:28:42.75", "best_dec": "-29:36:36.9", "best_alt": 8.4, "sun_elongation": 90.0, "moon_elongation": 108.0, "constelation": "Microscopium", "rise_time": "2025-11-06 18:20", "set_time": "2025-11-06 22:02", "motion": 2.89, "pa": 80.0, "trend": "steady"}, {"comet_type": "C", "comet_name": "C/2024 R4", "comet_fullname": "C/2024 R4 (PANSTARRS)", "mpc_name": "CK24R040", "best_time": "2025-11-06 19:06", "orbit_calc_source": 1, "magnitude": 16.9, "best_ra": "21:31:56.17", "best_dec": "22:00:52.1", "best_alt": 59.9, "sun_elongation": 106.0, "moon_elongation": 86.0, "constelation": "Pegasus", "rise_time": "2025-11-06 18:20", "set_time": "2025-11-07 03:14", "motion": 0.17, "pa": 232.0, "trend": "steady"}, {"comet_type": "P", "comet_name": "188P", "comet_fullname": "188P/LINEAR-Mueller", "mpc_name": "0188P", "best_time": "2025-11-06 19:18", "orbit_calc_source": 3, "magnitude": 17.9, "best_ra": "21:44:04.45", "best_dec": "-17:06:38.1", "best_alt": 20.8, "sun_elongation": 98.0, "moon_elongation": 100.0, "constelation": "Capricornus", "rise_time": "2025-11-06 18:20", "set_time": "2025-11-06 23:49", "motion": 0.48, "pa": 50.0, "trend": "steady"}, {"comet_type": "C", "comet_name": "C/2023 C2", "comet_fullname": "C/2023 C2 (ATLAS)", "mpc_name": "CK23C020", "best_time": "2025-11-06 19:52", "orbit_calc_source": 1, "magnitude": 16.7, "best_ra": "22:17:57.13", "best_dec": "53:56:57.3", "best_alt": 88.1, "sun_elongation": 116.0, "moon_elongation": 68.0, "constelation": "Lacerta", "rise_time": "2025-11-06 18:20", "set_time": "2025-11-07 06:26", "motion": 0.33, "pa": 173.0, "trend": "fade"}, {"comet_type": "P", "comet_name": "145P", "comet_fullname": "145P/Shoemaker-Levy", "mpc_name": "0145P", "best_time": "2025-11-06 20:00", "orbit_calc_source": 3, "magnitude": 17.5, "best_ra": "22:26:03.36", "best_dec": "-17:25:55.4", "best_alt": 20.5, "sun_elongation": 107.0, "moon_elongation": 91.0, "constelation": "Aquarius", "rise_time": "2025-11-06 18:20", "set_time": "2025-11-07 00:29", "motion": 0.67, "pa": 37.0, "trend": "steady"}, {"comet_type": "C", "comet_name": "C/2011 J2", "comet_fullname": "C/2011 J2 (LINEAR)", "mpc_name": "CK11J020", "best_time": "2025-11-06 20:06", "orbit_calc_source": 3, "magnitude": 18.6, "best_ra": "22:31:33.74", "best_dec": "-18:27:04.4", "best_alt": 19.5, "sun_elongation": 108.0, "moon_elongation": 91.0, "constelation": "Aquarius", "rise_time": "2025-11-06 18:20", "set_time": "2025-11-07 00:28", "motion": 0.13, "pa": 236.0, "trend": "fade"}, {"comet_type": "C", "comet_name": "C/2022 E2", "comet_fullname": "C/2022 E2 (ATLAS)", "mpc_name": "CK22E020", "best_time": "2025-11-06 20:13", "orbit_calc_source": 1, "magnitude": 15.9, "best_ra": "22:38:50.21", "best_dec": "43:40:34.9", "best_alt": 81.6, "sun_elongation": 121.0, "moon_elongation": 66.0, "constelation": "Lacerta", "rise_time": "2025-11-06 18:20", "set_time": "2025-11-07 06:26", "motion": 0.75, "pa": 206.0, "trend": "fade"}, {"comet_type": "C", "comet_name": "C/2025 R2", "comet_fullname": "C/2025 R2 (SWAN)", "mpc_name": "CK25R020", "best_time": "2025-11-06 20:15", "orbit_calc_source": 0, "magnitude": 8.5, "best_ra": "22:40:47.64", "best_dec": "1:56:26.7", "best_alt": 39.9, "sun_elongation": 117.0, "moon_elongation": 80.0, "constelation": "Aquarius", "rise_time": "2025-11-06 18:20", "set_time": "2025-11-07 02:30", "motion": 4.11, "pa": 73.0, "trend": "fade"}, {"comet_type": "P", "comet_name": "47P", "comet_fullname": "47P/Ashbrook-Jackson", "mpc_name": "0047P", "best_time": "2025-11-06 20:15", "orbit_calc_source": 1, "magnitude": 16.4, "best_ra": "22:41:11.25", "best_dec": "-8:14:02.5", "best_alt": 29.7, "sun_elongation": 114.0, "moon_elongation": 84.0, "constelation": "Aquarius", "rise_time": "2025-11-06 18:20", "set_time": "2025-11-07 01:35", "motion": 0.3, "pa": 33.0, "trend": "fade"}, {"comet_type": "P", "comet_name": "131P", "comet_fullname": "131P/Mueller", "mpc_name": "0131P", "best_time": "2025-11-06 20:25", "orbit_calc_source": 3, "magnitude": 16.3, "best_ra": "22:51:03.42", "best_dec": "-1:51:29.0", "best_alt": 36.1, "sun_elongation": 119.0, "moon_elongation": 79.0, "constelation": "Aquarius", "rise_time": "2025-11-06 18:20", "set_time": "2025-11-07 02:18", "motion": 0.27, "pa": 107.0, "trend": "fade"}, {"comet_type": "P", "comet_name": "295P", "comet_fullname": "295P/LINEAR", "mpc_name": "0295P", "best_time": "2025-11-06 20:33", "orbit_calc_source": 3, "magnitude": 18.8, "best_ra": "22:58:51.33", "best_dec": "-11:16:22.3", "best_alt": 26.7, "sun_elongation": 117.0, "moon_elongation": 82.0, "constelation": "Aquarius", "rise_time": "2025-11-06 18:20", "set_time": "2025-11-07 01:37", "motion": 0.27, "pa": 334.0, "trend": "steady"}, {"comet_type": "C", "comet_name": "C/2025 R3", "comet_fullname": "C/2025 R3 (PANSTARRS)", "mpc_name": "CK25R030", "best_time": "2025-11-06 20:53", "orbit_calc_source": 3, "magnitude": 18.4, "best_ra": "23:18:43.82", "best_dec": "34:15:30.1", "best_alt": 72.2, "sun_elongation": 130.0, "moon_elongation": 61.0, "constelation": "Pegasus", "rise_time": "2025-11-06 18:20", "set_time": "2025-11-07 06:26", "motion": 1.37, "pa": 241.0, "trend": "bright"}, {"comet_type": "N", "comet_name": "P/2016 G1", "comet_fullname": "P/2016 G1 (PANSTARRS)", "mpc_name": "PK16G010", "best_time": "2025-11-06 21:21", "orbit_calc_source": 3, "magnitude": 18.3, "best_ra": "23:47:12.73", "best_dec": "1:11:41.1", "best_alt": 39.1, "sun_elongation": 133.0, "moon_elongation": 66.0, "constelation": "Pisces", "rise_time": "2025-11-06 18:20", "set_time": "2025-11-07 03:30", "motion": 0.26, "pa": 154.0, "trend": "fade"}, {"comet_type": "P", "comet_name": "128P", "comet_fullname": "128P/Shoemaker-Holt", "mpc_name": "0128P", "best_time": "2025-11-06 21:43", "orbit_calc_source": 3, "magnitude": 15.7, "best_ra": "0:08:58.57", "best_dec": "3:07:51.7", "best_alt": 41.1, "sun_elongation": 139.0, "moon_elongation": 60.0, "constelation": "Pisces", "rise_time": "2025-11-06 18:20", "set_time": "2025-11-07 04:01", "motion": 0.2, "pa": 230.0, "trend": "steady"}, {"comet_type": "P", "comet_name": "302P", "comet_fullname": "302P/Lemmon-PANSTARRS", "mpc_name": "0302P", "best_time": "2025-11-06 21:54", "orbit_calc_source": 1, "magnitude": 16.6, "best_ra": "0:20:23.93", "best_dec": "-5:53:27.1", "best_alt": 32.0, "sun_elongation": 137.0, "moon_elongation": 63.0, "constelation": "Pisces", "rise_time": "2025-11-06 18:20", "set_time": "2025-11-07 03:26", "motion": 0.16, "pa": 267.0, "trend": "fade"}, {"comet_type": "P", "comet_name": "128P-B", "comet_fullname": "128P-B/Shoemaker-Holt", "mpc_name": "128P-B", "best_time": "2025-11-06 22:21", "orbit_calc_source": 3, "magnitude": 15.5, "best_ra": "0:47:20.64", "best_dec": "6:28:52.5", "best_alt": 44.4, "sun_elongation": 149.0, "moon_elongation": 51.0, "constelation": "Pisces", "rise_time": "2025-11-06 18:20", "set_time": "2025-11-07 04:57", "motion": 0.29, "pa": 236.0, "trend": "steady"}, {"comet_type": "N", "comet_name": "P/2023 M4", "comet_fullname": "P/2023 M4 (ATLAS)", "mpc_name": "PK23M040", "best_time": "2025-11-06 22:45", "orbit_calc_source": 3, "magnitude": 18.9, "best_ra": "1:11:07.55", "best_dec": "17:13:31.7", "best_alt": 55.1, "sun_elongation": 157.0, "moon_elongation": 41.0, "constelation": "Pisces", "rise_time": "2025-11-06 18:20", "set_time": "2025-11-07 06:21", "motion": 0.27, "pa": 242.0, "trend": "steady"}, {"comet_type": "A", "comet_name": "A/2025 S2", "comet_fullname": "A/2025 S2", "mpc_name": "AK25S020", "best_time": "2025-11-06 23:09", "orbit_calc_source": 3, "magnitude": 17.0, "best_ra": "1:35:45.78", "best_dec": "5:17:45.6", "best_alt": 43.2, "sun_elongation": 159.0, "moon_elongation": 41.0, "constelation": "Pisces", "rise_time": "2025-11-06 18:20", "set_time": "2025-11-07 05:38", "motion": 4.2, "pa": 291.0, "trend": "steady"}, {"comet_type": "P", "comet_name": "331P", "comet_fullname": "331P/Gibbs", "mpc_name": "0331P", "best_time": "2025-11-06 23:12", "orbit_calc_source": 3, "magnitude": 18.0, "best_ra": "1:38:13.14", "best_dec": "11:21:43.1", "best_alt": 49.3, "sun_elongation": 162.0, "moon_elongation": 38.0, "constelation": "Pisces", "rise_time": "2025-11-06 18:20", "set_time": "2025-11-07 06:14", "motion": 0.5, "pa": 233.0, "trend": "steady"}, {"comet_type": "P", "comet_name": "341P", "comet_fullname": "341P/Gibbs", "mpc_name": "0341P", "best_time": "2025-11-06 23:31", "orbit_calc_source": 3, "magnitude": 18.4, "best_ra": "1:57:45.21", "best_dec": "12:40:24.0", "best_alt": 50.6, "sun_elongation": 167.0, "moon_elongation": 33.0, "constelation": "Aries", "rise_time": "2025-11-06 18:20", "set_time": "2025-11-07 06:26", "motion": 0.42, "pa": 258.0, "trend": "fade"}, {"comet_type": "P", "comet_name": "513P", "comet_fullname": "513P/Broughton", "mpc_name": "0513P", "best_time": "2025-11-06 23:38", "orbit_calc_source": 3, "magnitude": 18.3, "best_ra": "2:04:30.96", "best_dec": "-0:44:21.8", "best_alt": 37.2, "sun_elongation": 160.0, "moon_elongation": 40.0, "constelation": "Cetus", "rise_time": "2025-11-06 18:20", "set_time": "2025-11-07 05:37", "motion": 0.44, "pa": 289.0, "trend": "fade"}, {"comet_type": "P", "comet_name": "37P", "comet_fullname": "37P/Forbes", "mpc_name": "0037P", "best_time": "2025-11-07 00:23", "orbit_calc_source": 3, "magnitude": 19.0, "best_ra": "2:49:23.01", "best_dec": "29:19:37.7", "best_alt": 67.2, "sun_elongation": 167.0, "moon_elongation": 18.0, "constelation": "Aries", "rise_time": "2025-11-06 18:20", "set_time": "2025-11-07 06:26", "motion": 0.56, "pa": 252.0, "trend": "fade"}, {"comet_type": "P", "comet_name": "82P", "comet_fullname": "82P/Gehrels", "mpc_name": "0082P", "best_time": "2025-11-07 00:58", "orbit_calc_source": 3, "magnitude": 18.9, "best_ra": "3:24:23.23", "best_dec": "18:52:26.2", "best_alt": 56.8, "sun_elongation": 171.0, "moon_elongation": 13.0, "constelation": "Aries", "rise_time": "2025-11-06 18:20", "set_time": "2025-11-07 06:26", "motion": 0.42, "pa": 255.0, "trend": "steady"}, {"comet_type": "C", "comet_name": "C/2022 N2", "comet_fullname": "C/2022 N2 (PANSTARRS)", "mpc_name": "CK22N020", "best_time": "2025-11-07 01:02", "orbit_calc_source": 0, "magnitude": 14.0, "best_ra": "3:28:58.88", "best_dec": "26:27:31.5", "best_alt": 64.4, "sun_elongation": 166.0, "moon_elongation": 9.0, "constelation": "Aries", "rise_time": "2025-11-06 18:20", "set_time": "2025-11-07 06:26", "motion": 0.25, "pa": 258.0, "trend": "steady"}, {"comet_type": "C", "comet_name": "C/2025 Q3", "comet_fullname": "C/2025 Q3 (ATLAS)", "mpc_name": "CK25Q030", "best_time": "2025-11-07 01:11", "orbit_calc_source": 3, "magnitude": 17.0, "best_ra": "3:37:39.76", "best_dec": "30:29:56.1", "best_alt": 68.4, "sun_elongation": 162.0, "moon_elongation": 9.0, "constelation": "Taurus", "rise_time": "2025-11-06 18:20", "set_time": "2025-11-07 06:26", "motion": 2.0, "pa": 218.0, "trend": "bright"}, {"comet_type": "P", "comet_name": "48P", "comet_fullname": "48P/Johnson", "mpc_name": "0048P", "best_time": "2025-11-07 01:15", "orbit_calc_source": 1, "magnitude": 16.7, "best_ra": "3:41:57.76", "best_dec": "2:42:41.8", "best_alt": 40.6, "sun_elongation": 161.0, "moon_elongation": 24.0, "constelation": "Taurus", "rise_time": "2025-11-06 18:59", "set_time": "2025-11-07 06:26", "motion": 0.57, "pa": 265.0, "trend": "fade"}, {"comet_type": "P", "comet_name": "240P", "comet_fullname": "240P/NEAT", "mpc_name": "0240P", "best_time": "2025-11-07 01:38", "orbit_calc_source": 0, "magnitude": 13.1, "best_ra": "4:04:24.49", "best_dec": "3:20:51.6", "best_alt": 41.3, "sun_elongation": 158.0, "moon_elongation": 22.0, "constelation": "Taurus", "rise_time": "2025-11-06 19:18", "set_time": "2025-11-07 06:26", "motion": 0.69, "pa": 305.0, "trend": "bright"}, {"comet_type": "P", "comet_name": "123P", "comet_fullname": "123P/West-Hartley", "mpc_name": "0123P", "best_time": "2025-11-07 01:45", "orbit_calc_source": 3, "magnitude": 18.1, "best_ra": "4:11:56.07", "best_dec": "26:16:47.5", "best_alt": 64.2, "sun_elongation": 158.0, "moon_elongation": 1.0, "constelation": "Taurus", "rise_time": "2025-11-06 18:20", "set_time": "2025-11-07 06:26", "motion": 0.48, "pa": 284.0, "trend": "bright"}, {"comet_type": "N", "comet_name": "P/2004 V5-B", "comet_fullname": "P/2004 V5-B (LINEAR-Hill)", "mpc_name": "PK04V05b", "best_time": "2025-11-07 01:59", "orbit_calc_source": 3, "magnitude": 18.8, "best_ra": "4:26:14.36", "best_dec": "28:49:05.7", "best_alt": 66.7, "sun_elongation": 155.0, "moon_elongation": 4.0, "constelation": "Taurus", "rise_time": "2025-11-06 18:20", "set_time": "2025-11-07 06:26", "motion": 0.28, "pa": 283.0, "trend": "steady"}, {"comet_type": "N", "comet_name": "P/2004 V5", "comet_fullname": "P/2004 V5 (LINEAR-Hill)", "mpc_name": "PK04V050", "best_time": "2025-11-07 02:00", "orbit_calc_source": 3, "magnitude": 18.8, "best_ra": "4:26:36.75", "best_dec": "28:51:36.2", "best_alt": 66.8, "sun_elongation": 154.0, "moon_elongation": 4.0, "constelation": "Taurus", "rise_time": "2025-11-06 18:20", "set_time": "2025-11-07 06:26", "motion": 0.28, "pa": 283.0, "trend": "steady"}, {"comet_type": "P", "comet_name": "136P", "comet_fullname": "136P/Mueller", "mpc_name": "0136P", "best_time": "2025-11-07 02:27", "orbit_calc_source": 3, "magnitude": 18.2, "best_ra": "4:54:24.59", "best_dec": "10:13:47.9", "best_alt": 48.2, "sun_elongation": 149.0, "moon_elongation": 18.0, "constelation": "Orion", "rise_time": "2025-11-06 19:31", "set_time": "2025-11-07 06:26", "motion": 0.35, "pa": 256.0, "trend": "steady"}, {"comet_type": "N", "comet_name": "P/2005 SB216", "comet_fullname": "P/2005 SB216 (LONEOS)", "mpc_name": "PK05SL6B", "best_time": "2025-11-07 02:47", "orbit_calc_source": 3, "magnitude": 17.4, "best_ra": "5:14:08.70", "best_dec": "52:07:51.4", "best_alt": 90.0, "sun_elongation": 134.0, "moon_elongation": 29.0, "constelation": "Auriga", "rise_time": "2025-11-06 18:20", "set_time": "2025-11-07 06:26", "motion": 0.31, "pa": 322.0, "trend": "steady"}, {"comet_type": "P", "comet_name": "493P", "comet_fullname": "493P/LONEOS", "mpc_name": "0493P", "best_time": "2025-11-07 02:47", "orbit_calc_source": 3, "magnitude": 17.4, "best_ra": "5:14:16.83", "best_dec": "52:07:41.8", "best_alt": 90.0, "sun_elongation": 134.0, "moon_elongation": 29.0, "constelation": "Auriga", "rise_time": "2025-11-06 18:20", "set_time": "2025-11-07 06:26", "motion": 0.31, "pa": 322.0, "trend": "steady"}, {"comet_type": "P", "comet_name": "509P", "comet_fullname": "509P/Catalina", "mpc_name": "0509P", "best_time": "2025-11-07 03:02", "orbit_calc_source": 3, "magnitude": 18.1, "best_ra": "5:29:31.46", "best_dec": "27:21:51.8", "best_alt": 65.3, "sun_elongation": 142.0, "moon_elongation": 17.0, "constelation": "Taurus", "rise_time": "2025-11-06 18:20", "set_time": "2025-11-07 06:26", "motion": 0.17, "pa": 253.0, "trend": "bright"}, {"comet_type": "N", "comet_name": "P/1999 XN120", "comet_fullname": "P/1999 XN120 (Catalina)", "mpc_name": "PJ99XC0N", "best_time": "2025-11-07 03:41", "orbit_calc_source": 3, "magnitude": 18.1, "best_ra": "6:08:32.20", "best_dec": "26:19:51.9", "best_alt": 64.2, "sun_elongation": 133.0, "moon_elongation": 25.0, "constelation": "Gemini", "rise_time": "2025-11-06 19:00", "set_time": "2025-11-07 06:26", "motion": 0.11, "pa": 262.0, "trend": "bright"}, {"comet_type": "C", "comet_name": "C/2017 K2", "comet_fullname": "C/2017 K2 (PANSTARRS)", "mpc_name": "CK17K020", "best_time": "2025-11-07 03:47", "orbit_calc_source": 1, "magnitude": 17.8, "best_ra": "6:14:17.42", "best_dec": "29:36:04.5", "best_alt": 67.5, "sun_elongation": 132.0, "moon_elongation": 26.0, "constelation": "Auriga", "rise_time": "2025-11-06 18:35", "set_time": "2025-11-07 06:26", "motion": 0.2, "pa": 292.0, "trend": "steady"}, {"comet_type": "C", "comet_name": "C/2022 L2", "comet_fullname": "C/2022 L2 (ATLAS)", "mpc_name": "CK22L020", "best_time": "2025-11-07 04:01", "orbit_calc_source": 3, "magnitude": 18.3, "best_ra": "6:28:44.06", "best_dec": "-24:11:18.9", "best_alt": 13.8, "sun_elongation": 113.0, "moon_elongation": 59.0, "constelation": "Canis Major", "rise_time": "2025-11-07 00:18", "set_time": "2025-11-07 06:26", "motion": 0.46, "pa": 251.0, "trend": "steady"}, {"comet_type": "P", "comet_name": "233P", "comet_fullname": "233P/La Sagra", "mpc_name": "0233P", "best_time": "2025-11-07 04:06", "orbit_calc_source": 3, "magnitude": 17.8, "best_ra": "6:33:30.59", "best_dec": "22:15:30.4", "best_alt": 60.2, "sun_elongation": 127.0, "moon_elongation": 31.0, "constelation": "Gemini", "rise_time": "2025-11-06 19:56", "set_time": "2025-11-07 06:26", "motion": 0.56, "pa": 53.0, "trend": "bright"}, {"comet_type": "P", "comet_name": "248P", "comet_fullname": "248P/Gibbs", "mpc_name": "0248P", "best_time": "2025-11-07 04:16", "orbit_calc_source": 3, "magnitude": 18.3, "best_ra": "6:43:30.13", "best_dec": "15:46:40.2", "best_alt": 53.7, "sun_elongation": 124.0, "moon_elongation": 35.0, "constelation": "Gemini", "rise_time": "2025-11-06 20:48", "set_time": "2025-11-07 06:26", "motion": 0.32, "pa": 133.0, "trend": "steady"}, {"comet_type": "P", "comet_name": "183P", "comet_fullname": "183P/Korlevic-Juric", "mpc_name": "0183P", "best_time": "2025-11-07 04:29", "orbit_calc_source": 3, "magnitude": 18.8, "best_ra": "6:55:55.58", "best_dec": "44:33:26.4", "best_alt": 82.5, "sun_elongation": 122.0, "moon_elongation": 37.0, "constelation": "Auriga", "rise_time": "2025-11-06 18:20", "set_time": "2025-11-07 06:26", "motion": 0.19, "pa": 344.0, "trend": "steady"}, {"comet_type": "P", "comet_name": "198P", "comet_fullname": "198P/ODAS", "mpc_name": "0198P", "best_time": "2025-11-07 04:45", "orbit_calc_source": 3, "magnitude": 16.2, "best_ra": "7:12:54.02", "best_dec": "24:23:30.5", "best_alt": 62.3, "sun_elongation": 118.0, "moon_elongation": 39.0, "constelation": "Gemini", "rise_time": "2025-11-06 20:19", "set_time": "2025-11-07 06:26", "motion": 0.43, "pa": 93.0, "trend": "bright"}, {"comet_type": "P", "comet_name": "74P", "comet_fullname": "74P/Smirnova-Chernykh", "mpc_name": "0074P", "best_time": "2025-11-07 04:53", "orbit_calc_source": 3, "magnitude": 18.4, "best_ra": "7:20:39.17", "best_dec": "27:00:25.6", "best_alt": 64.9, "sun_elongation": 117.0, "moon_elongation": 40.0, "constelation": "Gemini", "rise_time": "2025-11-06 20:06", "set_time": "2025-11-07 06:26", "motion": 0.06, "pa": 356.0, "trend": "bright"}, {"comet_type": "N", "comet_name": "P/2004 V5-A", "comet_fullname": "P/2004 V5-A (LINEAR-Hill)", "mpc_name": "PK04V05a", "best_time": "2025-11-07 04:56", "orbit_calc_source": 3, "magnitude": 18.0, "best_ra": "7:23:36.04", "best_dec": "40:07:24.8", "best_alt": 78.0, "sun_elongation": 117.0, "moon_elongation": 41.0, "constelation": "Auriga", "rise_time": "2025-11-06 18:20", "set_time": "2025-11-07 06:26", "motion": 0.2, "pa": 14.0, "trend": "bright"}, {"comet_type": "P", "comet_name": "186P", "comet_fullname": "186P/Garradd", "mpc_name": "0186P", "best_time": "2025-11-07 05:24", "orbit_calc_source": 3, "magnitude": 18.1, "best_ra": "7:51:32.15", "best_dec": "44:52:30.1", "best_alt": 82.8, "sun_elongation": 112.0, "moon_elongation": 46.0, "constelation": "Lynx", "rise_time": "2025-11-06 18:20", "set_time": "2025-11-07 06:26", "motion": 0.1, "pa": 358.0, "trend": "bright"}, {"comet_type": "P", "comet_name": "450P", "comet_fullname": "450P/LONEOS", "mpc_name": "0450P", "best_time": "2025-11-07 05:36", "orbit_calc_source": 3, "magnitude": 17.8, "best_ra": "8:03:02.59", "best_dec": "17:25:15.1", "best_alt": 55.3, "sun_elongation": 106.0, "moon_elongation": 52.0, "constelation": "Cancer", "rise_time": "2025-11-06 21:57", "set_time": "2025-11-07 06:26", "motion": 0.08, "pa": 90.0, "trend": "bright"}, {"comet_type": "P", "comet_name": "242P", "comet_fullname": "242P/Spahr", "mpc_name": "0242P", "best_time": "2025-11-07 05:39", "orbit_calc_source": 3, "magnitude": 17.3, "best_ra": "8:07:01.98", "best_dec": "-13:10:17.6", "best_alt": 24.8, "sun_elongation": 96.0, "moon_elongation": 68.0, "constelation": "Puppis", "rise_time": "2025-11-07 00:46", "set_time": "2025-11-07 06:26", "motion": 0.29, "pa": 153.0, "trend": "steady"}, {"comet_type": "P", "comet_name": "24P", "comet_fullname": "24P/Schaumasse", "mpc_name": "0024P", "best_time": "2025-11-07 06:06", "orbit_calc_source": 3, "magnitude": 11.7, "best_ra": "8:33:34.22", "best_dec": "20:07:26.9", "best_alt": 58.0, "sun_elongation": 99.0, "moon_elongation": 58.0, "constelation": "Cancer", "rise_time": "2025-11-06 22:09", "set_time": "2025-11-07 06:26", "motion": 2.3, "pa": 90.0, "trend": "bright"}, {"comet_type": "C", "comet_name": "C/2024 A1", "comet_fullname": "C/2024 A1 (ATLAS)", "mpc_name": "CK24A010", "best_time": "2025-11-07 06:26", "orbit_calc_source": 1, "magnitude": 16.6, "best_ra": "8:57:14.38", "best_dec": "38:39:26.7", "best_alt": 76.6, "sun_elongation": 99.0, "moon_elongation": 58.0, "constelation": "Lynx", "rise_time": "2025-11-06 18:20", "set_time": "2025-11-07 06:26", "motion": 0.68, "pa": 5.0, "trend": "steady"}, {"comet_type": "C", "comet_name": "C/2022 R6", "comet_fullname": "C/2022 R6 (PANSTARRS)", "mpc_name": "CK22R060", "best_time": "2025-11-07 06:26", "orbit_calc_source": 1, "magnitude": 16.4, "best_ra": "8:57:24.07", "best_dec": "-11:58:40.7", "best_alt": 26.0, "sun_elongation": 85.0, "moon_elongation": 77.0, "constelation": "Hydra", "rise_time": "2025-11-07 01:30", "set_time": "2025-11-07 06:26", "motion": 0.14, "pa": 111.0, "trend": "steady"}, {"comet_type": "P", "comet_name": "217P", "comet_fullname": "217P/LINEAR", "mpc_name": "0217P", "best_time": "2025-11-07 06:26", "orbit_calc_source": 1, "magnitude": 16.7, "best_ra": "9:10:55.12", "best_dec": "12:19:19.7", "best_alt": 50.1, "sun_elongation": 89.0, "moon_elongation": 69.0, "constelation": "Cancer", "rise_time": "2025-11-06 23:35", "set_time": "2025-11-07 06:26", "motion": 0.42, "pa": 93.0, "trend": "fade"}, {"comet_type": "P", "comet_name": "124P", "comet_fullname": "124P/Mrkos", "mpc_name": "0124P", "best_time": "2025-11-07 06:26", "orbit_calc_source": 3, "magnitude": 18.1, "best_ra": "9:17:01.15", "best_dec": "55:00:12.4", "best_alt": 85.5, "sun_elongation": 100.0, "moon_elongation": 60.0, "constelation": "Ursa Major", "rise_time": "2025-11-06 18:20", "set_time": "2025-11-07 06:26", "motion": 0.66, "pa": 69.0, "trend": "bright"}, {"comet_type": "C", "comet_name": "C/2022 QE78", "comet_fullname": "C/2022 QE78 (ATLAS)", "mpc_name": "CK22Q78E", "best_time": "2025-11-07 06:26", "orbit_calc_source": 1, "magnitude": 15.4, "best_ra": "9:19:17.80", "best_dec": "19:53:37.6", "best_alt": 57.4, "sun_elongation": 89.0, "moon_elongation": 68.0, "constelation": "Cancer", "rise_time": "2025-11-06 22:58", "set_time": "2025-11-07 06:26", "motion": 0.29, "pa": 66.0, "trend": "steady"}, {"comet_type": "C", "comet_name": "C/2024 X2", "comet_fullname": "C/2024 X2 (ATLAS)", "mpc_name": "CK24X020", "best_time": "2025-11-07 06:26", "orbit_calc_source": 3, "magnitude": 18.4, "best_ra": "9:26:10.44", "best_dec": "-5:35:12.0", "best_alt": 31.9, "sun_elongation": 80.0, "moon_elongation": 80.0, "constelation": "Hydra", "rise_time": "2025-11-07 01:25", "set_time": "2025-11-07 06:26", "motion": 0.21, "pa": 350.0, "trend": "steady"}, {"comet_type": "C", "comet_name": "C/2025 D1", "comet_fullname": "C/2025 D1 (Groeller)", "mpc_name": "CK25D010", "best_time": "2025-11-07 06:26", "orbit_calc_source": 3, "magnitude": 18.7, "best_ra": "9:36:34.90", "best_dec": "32:57:47.3", "best_alt": 69.4, "sun_elongation": 90.0, "moon_elongation": 67.0, "constelation": "Leo Minor", "rise_time": "2025-11-06 21:17", "set_time": "2025-11-07 06:26", "motion": 0.01, "pa": 179.0, "trend": "steady"}, {"comet_type": "P", "comet_name": "195P", "comet_fullname": "195P/Hill", "mpc_name": "0195P", "best_time": "2025-11-07 06:26", "orbit_calc_source": 3, "magnitude": 18.4, "best_ra": "9:46:14.65", "best_dec": "-22:58:26.9", "best_alt": 14.1, "sun_elongation": 71.0, "moon_elongation": 92.0, "constelation": "Hydra", "rise_time": "2025-11-07 03:26", "set_time": "2025-11-07 06:26", "motion": 0.54, "pa": 143.0, "trend": "steady"}, {"comet_type": "P", "comet_name": "171P", "comet_fullname": "171P/Spahr", "mpc_name": "0171P", "best_time": "2025-11-07 06:26", "orbit_calc_source": 3, "magnitude": 17.2, "best_ra": "9:47:16.54", "best_dec": "17:11:55.0", "best_alt": 53.6, "sun_elongation": 82.0, "moon_elongation": 75.0, "constelation": "Leo", "rise_time": "2025-11-06 23:42", "set_time": "2025-11-07 06:26", "motion": 1.27, "pa": 84.0, "trend": "steady"}, {"comet_type": "P", "comet_name": "21P", "comet_fullname": "21P/Giacobini-Zinner", "mpc_name": "0021P", "best_time": "2025-11-07 06:26", "orbit_calc_source": 3, "magnitude": 18.0, "best_ra": "9:53:55.91", "best_dec": "-16:03:08.8", "best_alt": 20.7, "sun_elongation": 71.0, "moon_elongation": 91.0, "constelation": "Hydra", "rise_time": "2025-11-07 02:49", "set_time": "2025-11-07 06:26", "motion": 0.55, "pa": 136.0, "trend": "fade"}, {"comet_type": "P", "comet_name": "472P", "comet_fullname": "472P/NEAT-LINEAR", "mpc_name": "0472P", "best_time": "2025-11-07 06:26", "orbit_calc_source": 1, "magnitude": 17.8, "best_ra": "10:06:05.65", "best_dec": "1:37:00.6", "best_alt": 37.4, "sun_elongation": 72.0, "moon_elongation": 85.0, "constelation": "Sextans", "rise_time": "2025-11-07 01:27", "set_time": "2025-11-07 06:26", "motion": 0.37, "pa": 119.0, "trend": "steady"}, {"comet_type": "P", "comet_name": "489P", "comet_fullname": "489P/Denning", "mpc_name": "0489P", "best_time": "2025-11-07 06:26", "orbit_calc_source": 3, "magnitude": 18.4, "best_ra": "10:15:01.73", "best_dec": "15:20:23.0", "best_alt": 49.9, "sun_elongation": 75.0, "moon_elongation": 82.0, "constelation": "Leo", "rise_time": "2025-11-07 00:21", "set_time": "2025-11-07 06:26", "motion": 1.8, "pa": 110.0, "trend": "bright"}, {"comet_type": "C", "comet_name": "C/2023 X2", "comet_fullname": "C/2023 X2 (Lemmon)", "mpc_name": "CK23X020", "best_time": "2025-11-07 06:26", "orbit_calc_source": 3, "magnitude": 17.6, "best_ra": "10:16:25.48", "best_dec": "82:40:59.8", "best_alt": 58.9, "sun_elongation": 104.0, "moon_elongation": 64.0, "constelation": "Camelopardalis", "rise_time": "2025-11-06 18:20", "set_time": "2025-11-07 06:26", "motion": 0.64, "pa": 44.0, "trend": "steady"}, {"comet_type": "P", "comet_name": "43P", "comet_fullname": "43P/Wolf-Harrington", "mpc_name": "0043P", "best_time": "2025-11-07 06:26", "orbit_calc_source": 1, "magnitude": 16.3, "best_ra": "10:25:49.39", "best_dec": "1:00:36.1", "best_alt": 35.5, "sun_elongation": 67.0, "moon_elongation": 90.0, "constelation": "Sextans", "rise_time": "2025-11-07 01:50", "set_time": "2025-11-07 06:26", "motion": 0.92, "pa": 119.0, "trend": "steady"}, {"comet_type": "P", "comet_name": "187P", "comet_fullname": "187P/LINEAR", "mpc_name": "0187P", "best_time": "2025-11-07 06:26", "orbit_calc_source": 3, "magnitude": 19.0, "best_ra": "10:26:25.85", "best_dec": "16:53:48.6", "best_alt": 50.4, "sun_elongation": 73.0, "moon_elongation": 83.0, "constelation": "Leo", "rise_time": "2025-11-07 00:24", "set_time": "2025-11-07 06:26", "motion": 0.39, "pa": 97.0, "trend": "bright"}, {"comet_type": "P", "comet_name": "164P", "comet_fullname": "164P/Christensen", "mpc_name": "0164P", "best_time": "2025-11-07 06:26", "orbit_calc_source": 3, "magnitude": 16.4, "best_ra": "10:35:34.03", "best_dec": "19:43:02.5", "best_alt": 52.1, "sun_elongation": 72.0, "moon_elongation": 84.0, "constelation": "Leo", "rise_time": "2025-11-07 00:15", "set_time": "2025-11-07 06:26", "motion": 0.88, "pa": 93.0, "trend": "steady"}, {"comet_type": "C", "comet_name": "C/2023 F3", "comet_fullname": "C/2023 F3 (ATLAS)", "mpc_name": "CK23F030", "best_time": "2025-11-07 06:26", "orbit_calc_source": 3, "magnitude": 17.4, "best_ra": "11:04:27.96", "best_dec": "-23:43:03.9", "best_alt": 9.1, "sun_elongation": 53.0, "moon_elongation": 109.0, "constelation": "Crater", "rise_time": "2025-11-07 04:50", "set_time": "2025-11-07 06:26", "motion": 0.1, "pa": 186.0, "trend": "steady"}, {"comet_type": "P", "comet_name": "29P", "comet_fullname": "29P/Schwassmann-Wachmann", "mpc_name": "0029P", "best_time": "2025-11-07 06:26", "orbit_calc_source": 1, "magnitude": 12.7, "best_ra": "11:20:16.91", "best_dec": "-0:35:17.3", "best_alt": 29.1, "sun_elongation": 54.0, "moon_elongation": 103.0, "constelation": "Leo", "rise_time": "2025-11-07 02:52", "set_time": "2025-11-07 06:26", "motion": 0.35, "pa": 120.0, "trend": "steady"}, {"comet_type": "C", "comet_name": "C/2025 J1", "comet_fullname": "C/2025 J1 (Borisov)", "mpc_name": "CK25J010", "best_time": "2025-11-07 06:26", "orbit_calc_source": 3, "magnitude": 18.1, "best_ra": "11:20:19.56", "best_dec": "71:45:04.5", "best_alt": 64.7, "sun_elongation": 95.0, "moon_elongation": 70.0, "constelation": "Ursa Major", "rise_time": "2025-11-06 18:20", "set_time": "2025-11-07 06:26", "motion": 0.33, "pa": 351.0, "trend": "bright"}, {"comet_type": "C", "comet_name": "C/2024 L5", "comet_fullname": "C/2024 L5 (ATLAS)", "mpc_name": "CK24L050", "best_time": "2025-11-07 06:26", "orbit_calc_source": 1, "magnitude": 18.0, "best_ra": "11:24:43.72", "best_dec": "-1:03:17.8", "best_alt": 28.2, "sun_elongation": 53.0, "moon_elongation": 104.0, "constelation": "Leo", "rise_time": "2025-11-07 02:59", "set_time": "2025-11-07 06:26", "motion": 0.05, "pa": 329.0, "trend": "steady"}, {"comet_type": "C", "comet_name": "C/2025 K1", "comet_fullname": "C/2025 K1 (ATLAS)", "mpc_name": "CK25K010", "best_time": "2025-11-07 06:26", "orbit_calc_source": 0, "magnitude": 9.8, "best_ra": "11:29:49.02", "best_dec": "12:52:19.5", "best_alt": 39.9, "sun_elongation": 58.0, "moon_elongation": 99.0, "constelation": "Leo", "rise_time": "2025-11-07 01:53", "set_time": "2025-11-07 06:26", "motion": 4.1, "pa": 344.0, "trend": "fade"}, {"comet_type": "C", "comet_name": "C/2024 G2", "comet_fullname": "C/2024 G2 (ATLAS)", "mpc_name": "CK24G020", "best_time": "2025-11-07 06:26", "orbit_calc_source": 3, "magnitude": 18.3, "best_ra": "12:05:55.96", "best_dec": "-12:48:30.3", "best_alt": 13.2, "sun_elongation": 40.0, "moon_elongation": 119.0, "constelation": "Corvus", "rise_time": "2025-11-07 04:43", "set_time": "2025-11-07 06:26", "motion": 0.22, "pa": 74.0, "trend": "steady"}, {"comet_type": "P", "comet_name": "235P", "comet_fullname": "235P/LINEAR", "mpc_name": "0235P", "best_time": "2025-11-07 06:26", "orbit_calc_source": 3, "magnitude": 17.2, "best_ra": "12:33:02.03", "best_dec": "-7:04:48.5", "best_alt": 14.8, "sun_elongation": 35.0, "moon_elongation": 122.0, "constelation": "Virgo", "rise_time": "2025-11-07 04:38", "set_time": "2025-11-07 06:26", "motion": 1.47, "pa": 109.0, "trend": "bright"}, {"comet_type": "P", "comet_name": "60P", "comet_fullname": "60P/Tsuchinshan", "mpc_name": "0060P", "best_time": "2025-11-07 06:26", "orbit_calc_source": 3, "magnitude": 18.0, "best_ra": "12:53:21.68", "best_dec": "-8:27:38.8", "best_alt": 11.0, "sun_elongation": 30.0, "moon_elongation": 127.0, "constelation": "Virgo", "rise_time": "2025-11-07 05:06", "set_time": "2025-11-07 06:26", "motion": 1.42, "pa": 113.0, "trend": "fade"}, {"comet_type": "P", "comet_name": "40P", "comet_fullname": "40P/Vaisala", "mpc_name": "0040P", "best_time": "2025-11-07 06:26", "orbit_calc_source": 3, "magnitude": 15.4, "best_ra": "13:03:02.95", "best_dec": "-0:00:40.5", "best_alt": 16.7, "sun_elongation": 31.0, "moon_elongation": 125.0, "constelation": "Virgo", "rise_time": "2025-11-07 04:32", "set_time": "2025-11-07 06:26", "motion": 1.68, "pa": 108.0, "trend": "steady"}, {"comet_type": "C", "comet_name": "C/2025 V1", "comet_fullname": "C/2025 V1 (Borisov)", "mpc_name": "CK25V010", "best_time": "2025-11-07 06:26", "orbit_calc_source": 3, "magnitude": 12.7, "best_ra": "13:06:07.84", "best_dec": "-0:19:46.0", "best_alt": 16.0, "sun_elongation": 30.0, "moon_elongation": 126.0, "constelation": "Virgo", "rise_time": "2025-11-07 04:36", "set_time": "2025-11-07 06:26", "motion": 8.82, "pa": 71.0, "trend": "bright"}, {"comet_type": "I", "comet_name": "3I", "comet_fullname": "3I/ATLAS", "mpc_name": "0003I", "best_time": "2025-11-07 06:26", "orbit_calc_source": 1, "magnitude": 11.2, "best_ra": "13:11:31.74", "best_dec": "-5:32:54.6", "best_alt": 10.9, "sun_elongation": 27.0, "moon_elongation": 130.0, "constelation": "Virgo", "rise_time": "2025-11-07 05:09", "set_time": "2025-11-07 06:26", "motion": 1.54, "pa": 288.0, "trend": "fade"}, {"comet_type": "N", "comet_name": "P/2023 S1", "comet_fullname": "P/2023 S1", "mpc_name": "PK23S010", "best_time": "2025-11-07 06:26", "orbit_calc_source": 1, "magnitude": 18.1, "best_ra": "13:26:57.05", "best_dec": "-15:48:31.4", "best_alt": 0.7, "sun_elongation": 20.0, "moon_elongation": 138.0, "constelation": "Virgo", "rise_time": "2025-11-07 06:21", "set_time": "2025-11-07 06:26", "motion": 0.97, "pa": 115.0, "trend": "steady"}, {"comet_type": "P", "comet_name": "10P", "comet_fullname": "10P/Tempel 2", "mpc_name": "0010P", "best_time": "2025-11-07 06:26", "orbit_calc_source": 3, "magnitude": 18.9, "best_ra": "13:52:30.93", "best_dec": "-2:00:02.8", "best_alt": 7.9, "sun_elongation": 20.0, "moon_elongation": 137.0, "constelation": "Virgo", "rise_time": "2025-11-07 05:32", "set_time": "2025-11-07 06:26", "motion": 1.02, "pa": 109.0, "trend": "bright"}, {"comet_type": "P", "comet_name": "391P", "comet_fullname": "391P/Kowalski", "mpc_name": "0391P", "best_time": "2025-11-07 06:26", "orbit_calc_source": 3, "magnitude": 18.5, "best_ra": "14:24:07.04", "best_dec": "4:21:30.3", "best_alt": 8.2, "sun_elongation": 22.0, "moon_elongation": 138.0, "constelation": "Virgo", "rise_time": "2025-11-07 05:30", "set_time": "2025-11-07 06:26", "motion": 0.63, "pa": 107.0, "trend": "steady"}], "signature": {"source": "COBS Query API", "version": "1.2", "date": "2024 Sep"}}